{"slate_date":"2026-06-30","last_refreshed":"2026-06-30T17:30:01-04:00","lineup_status":"confirmed","refresh_note":"Projections update on confirmed lineups throughout the day. Best Bets shows today's locked morning picks.","games":[{"away_team":"NYM","home_team":"TOR","time":"7:07 PM ET","away_score":null,"home_score":null,"winner":"","lineup_status":"confirmed","batters":[{"team":"TOR","player":"Clement, Ernie","proj_hits":0.909,"proj_tb":1.657,"proj_hr":0.033,"proj_bb":0.177,"l10_hit_pct":0.6,"vp_pa":null,"vp_h":null,"vp_hr":null,"vp_xwoba":null,"h_streak":null,"hrr_streak":null,"book_hits_line":null},{"team":"TOR","player":"Guerrero Jr., Vladimir","proj_hits":0.729,"proj_tb":1.164,"proj_hr":0.014,"proj_bb":0.217,"l10_hit_pct":0.5,"vp_pa":null,"vp_h":null,"vp_hr":null,"vp_xwoba":null,"h_streak":null,"hrr_streak":null,"book_hits_line":null},{"team":"TOR","player":"Kirk, Alejandro","proj_hits":0.483,"proj_tb":1.093,"proj_hr":0.137,"proj_bb":0.086,"l10_hit_pct":0.4,"vp_pa":null,"vp_h":null,"vp_hr":null,"vp_xwoba":null,"h_streak":null,"hrr_streak":null,"book_hits_line":null},{"team":"TOR","player":"Lukes, Nathan","proj_hits":0.689,"proj_tb":1.557,"proj_hr":0.157,"proj_bb":0.258,"l10_hit_pct":0.6,"vp_pa":null,"vp_h":null,"vp_hr":null,"vp_xwoba":null,"h_streak":null,"hrr_streak":null,"book_hits_line":null},{"team":"TOR","player":"Okamoto, Kazuma","proj_hits":0.789,"proj_tb":2.306,"proj_hr":0.358,"proj_bb":0.334,"l10_hit_pct":0.5,"vp_pa":null,"vp_h":null,"vp_hr":null,"vp_xwoba":null,"h_streak":null,"hrr_streak":null,"book_hits_line":null},{"team":"TOR","player":"Springer, George","proj_hits":0.784,"proj_tb":1.804,"proj_hr":0.129,"proj_bb":0.387,"l10_hit_pct":0.7,"vp_pa":null,"vp_h":null,"vp_hr":null,"vp_xwoba":null,"h_streak":null,"hrr_streak":null,"book_hits_line":null},{"team":"TOR","player":"Straw, Myles","proj_hits":0.369,"proj_tb":0.708,"proj_hr":0.01,"proj_bb":0.184,"l10_hit_pct":0.4,"vp_pa":null,"vp_h":null,"vp_hr":null,"vp_xwoba":null,"h_streak":null,"hrr_streak":null,"book_hits_line":null},{"team":"TOR","player":"Valenzuela, Brandon","proj_hits":0.549,"proj_tb":1.128,"proj_hr":0.055,"proj_bb":0.427,"l10_hit_pct":0.5,"vp_pa":null,"vp_h":null,"vp_hr":null,"vp_xwoba":null,"h_streak":null,"hrr_streak":null,"book_hits_line":null},{"team":"TOR","player":"Varsho, Daulton","proj_hits":0.732,"proj_tb":1.801,"proj_hr":0.179,"proj_bb":0.343,"l10_hit_pct":0.6,"vp_pa":null,"vp_h":null,"vp_hr":null,"vp_xwoba":null,"h_streak":null,"hrr_streak":null,"book_hits_line":null},{"team":"NYM","player":"Alvarez, Francisco","proj_hits":0.774,"proj_tb":1.848,"proj_hr":0.244,"proj_bb":0.214,"l10_hit_pct":0.6,"vp_pa":null,"vp_h":null,"vp_hr":null,"vp_xwoba":null,"h_streak":null,"hrr_streak":null,"book_hits_line":null},{"team":"NYM","player":"Baty, Brett","proj_hits":0.375,"proj_tb":0.541,"proj_hr":0.015,"proj_bb":0.441,"l10_hit_pct":0.2,"vp_pa":null,"vp_h":null,"vp_hr":null,"vp_xwoba":null,"h_streak":null,"hrr_streak":null,"book_hits_line":null},{"team":"NYM","player":"Benge, Carson","proj_hits":0.933,"proj_tb":1.995,"proj_hr":0.197,"proj_bb":0.318,"l10_hit_pct":0.9,"vp_pa":null,"vp_h":null,"vp_hr":null,"vp_xwoba":null,"h_streak":null,"hrr_streak":null,"book_hits_line":null},{"team":"NYM","player":"Bichette, Bo","proj_hits":0.954,"proj_tb":1.972,"proj_hr":0.168,"proj_bb":0.188,"l10_hit_pct":0.8,"vp_pa":null,"vp_h":null,"vp_hr":null,"vp_xwoba":null,"h_streak":null,"hrr_streak":null,"book_hits_line":null},{"team":"NYM","player":"Ewing, A.J.","proj_hits":0.874,"proj_tb":1.658,"proj_hr":0.16,"proj_bb":0.414,"l10_hit_pct":0.6,"vp_pa":null,"vp_h":null,"vp_hr":null,"vp_xwoba":null,"h_streak":null,"hrr_streak":null,"book_hits_line":null},{"team":"NYM","player":"Lindor, Francisco","proj_hits":0.796,"proj_tb":1.925,"proj_hr":0.193,"proj_bb":0.263,"l10_hit_pct":0.7,"vp_pa":13,"vp_h":4,"vp_hr":1,"vp_xwoba":0.496,"h_streak":null,"hrr_streak":null,"book_hits_line":null},{"team":"NYM","player":"Mauricio, Ronny","proj_hits":0.49,"proj_tb":1.087,"proj_hr":0.113,"proj_bb":0.021,"l10_hit_pct":0.5,"vp_pa":null,"vp_h":null,"vp_hr":null,"vp_xwoba":null,"h_streak":null,"hrr_streak":null,"book_hits_line":null},{"team":"NYM","player":"Soto, Juan","proj_hits":0.964,"proj_tb":2.363,"proj_hr":0.266,"proj_bb":0.714,"l10_hit_pct":0.8,"vp_pa":29,"vp_h":8,"vp_hr":1,"vp_xwoba":0.6,"h_streak":null,"hrr_streak":null,"book_hits_line":null},{"team":"NYM","player":"Torrens, Luis","proj_hits":0.565,"proj_tb":0.879,"proj_hr":0.008,"proj_bb":0.1,"l10_hit_pct":0.5,"vp_pa":2,"vp_h":0,"vp_hr":0,"vp_xwoba":0.0,"h_streak":null,"hrr_streak":null,"book_hits_line":null},{"team":"NYM","player":"Vientos, Mark","proj_hits":0.539,"proj_tb":1.395,"proj_hr":0.225,"proj_bb":0.278,"l10_hit_pct":0.3,"vp_pa":2,"vp_h":0,"vp_hr":0,"vp_xwoba":0.0,"h_streak":null,"hrr_streak":null,"book_hits_line":null},{"team":"NYM","player":"Wagaman, Eric","proj_hits":0.412,"proj_tb":0.95,"proj_hr":0.128,"proj_bb":0.098,"l10_hit_pct":0.4,"vp_pa":3,"vp_h":2,"vp_hr":1,"vp_xwoba":0.967,"h_streak":null,"hrr_streak":null,"book_hits_line":null},{"team":"NYM","player":"Young, Jared","proj_hits":0.614,"proj_tb":1.496,"proj_hr":0.2,"proj_bb":0.252,"l10_hit_pct":0.5,"vp_pa":null,"vp_h":null,"vp_hr":null,"vp_xwoba":null,"h_streak":null,"hrr_streak":null,"book_hits_line":null}]},{"away_team":"LAA","home_team":"SEA","time":"9:40 PM ET","away_score":null,"home_score":null,"winner":"","lineup_status":"confirmed","batters":[{"team":"SEA","player":"Arozarena, Randy","proj_hits":0.826,"proj_tb":1.444,"proj_hr":0.131,"proj_bb":0.374,"l10_hit_pct":0.4,"vp_pa":13,"vp_h":4,"vp_hr":0,"vp_xwoba":0.438,"h_streak":null,"hrr_streak":null,"book_hits_line":null},{"team":"SEA","player":"Canzone, Dominic","proj_hits":0.655,"proj_tb":1.534,"proj_hr":0.235,"proj_bb":0.384,"l10_hit_pct":0.4,"vp_pa":7,"vp_h":0,"vp_hr":0,"vp_xwoba":0.1,"h_streak":null,"hrr_streak":null,"book_hits_line":null},{"team":"SEA","player":"Crawford, J.P.","proj_hits":0.846,"proj_tb":1.233,"proj_hr":0.057,"proj_bb":0.354,"l10_hit_pct":0.6,"vp_pa":16,"vp_h":5,"vp_hr":0,"vp_xwoba":0.391,"h_streak":null,"hrr_streak":null,"book_hits_line":null},{"team":"SEA","player":"Emerson, Colt","proj_hits":0.444,"proj_tb":1.099,"proj_hr":0.167,"proj_bb":0.376,"l10_hit_pct":0.3,"vp_pa":null,"vp_h":null,"vp_hr":null,"vp_xwoba":null,"h_streak":null,"hrr_streak":null,"book_hits_line":null},{"team":"SEA","player":"Garver, Mitch","proj_hits":0.462,"proj_tb":0.876,"proj_hr":0.084,"proj_bb":0.419,"l10_hit_pct":0.4,"vp_pa":3,"vp_h":0,"vp_hr":0,"vp_xwoba":0.467,"h_streak":null,"hrr_streak":null,"book_hits_line":null},{"team":"SEA","player":"Naylor, Josh","proj_hits":0.959,"proj_tb":1.553,"proj_hr":0.039,"proj_bb":0.355,"l10_hit_pct":0.7,"vp_pa":16,"vp_h":2,"vp_hr":0,"vp_xwoba":0.113,"h_streak":null,"hrr_streak":null,"book_hits_line":null},{"team":"SEA","player":"Raleigh, Cal","proj_hits":0.784,"proj_tb":1.365,"proj_hr":0.149,"proj_bb":0.777,"l10_hit_pct":0.6,"vp_pa":17,"vp_h":3,"vp_hr":0,"vp_xwoba":0.282,"h_streak":null,"hrr_streak":null,"book_hits_line":null},{"team":"SEA","player":"Raley, Luke","proj_hits":0.606,"proj_tb":1.368,"proj_hr":0.168,"proj_bb":0.25,"l10_hit_pct":0.5,"vp_pa":12,"vp_h":0,"vp_hr":0,"vp_xwoba":0.133,"h_streak":null,"hrr_streak":null,"book_hits_line":null},{"team":"SEA","player":"Robles, Victor","proj_hits":0.641,"proj_tb":0.825,"proj_hr":0.0,"proj_bb":0.181,"l10_hit_pct":0.5,"vp_pa":5,"vp_h":2,"vp_hr":0,"vp_xwoba":0.357,"h_streak":null,"hrr_streak":null,"book_hits_line":null},{"team":"SEA","player":"Wilson, Weston","proj_hits":0.435,"proj_tb":0.697,"proj_hr":0.081,"proj_bb":0.099,"l10_hit_pct":0.3,"vp_pa":null,"vp_h":null,"vp_hr":null,"vp_xwoba":null,"h_streak":null,"hrr_streak":null,"book_hits_line":null},{"team":"SEA","player":"Young, Cole","proj_hits":0.972,"proj_tb":1.986,"proj_hr":0.232,"proj_bb":0.249,"l10_hit_pct":0.7,"vp_pa":2,"vp_h":0,"vp_hr":0,"vp_xwoba":0.0,"h_streak":null,"hrr_streak":null,"book_hits_line":null},{"team":"LAA","player":"Adell, Jo","proj_hits":0.716,"proj_tb":1.717,"proj_hr":0.141,"proj_bb":0.105,"l10_hit_pct":0.6,"vp_pa":12,"vp_h":5,"vp_hr":3,"vp_xwoba":0.737,"h_streak":null,"hrr_streak":null,"book_hits_line":null},{"team":"LAA","player":"Grissom, Vaughn","proj_hits":0.717,"proj_tb":1.477,"proj_hr":0.125,"proj_bb":0.227,"l10_hit_pct":0.7,"vp_pa":null,"vp_h":null,"vp_hr":null,"vp_xwoba":null,"h_streak":null,"hrr_streak":null,"book_hits_line":null},{"team":"LAA","player":"Guzman, Denzer","proj_hits":0.848,"proj_tb":2.117,"proj_hr":0.338,"proj_bb":0.465,"l10_hit_pct":0.7,"vp_pa":2,"vp_h":0,"vp_hr":0,"vp_xwoba":0.0,"h_streak":null,"hrr_streak":null,"book_hits_line":null},{"team":"LAA","player":"Heineman, Tyler","proj_hits":0.416,"proj_tb":0.818,"proj_hr":0.076,"proj_bb":0.142,"l10_hit_pct":0.4,"vp_pa":null,"vp_h":null,"vp_hr":null,"vp_xwoba":null,"h_streak":null,"hrr_streak":null,"book_hits_line":null},{"team":"LAA","player":"Lowe, Josh","proj_hits":0.724,"proj_tb":1.582,"proj_hr":0.2,"proj_bb":0.042,"l10_hit_pct":0.9,"vp_pa":9,"vp_h":2,"vp_hr":0,"vp_xwoba":0.239,"h_streak":null,"hrr_streak":null,"book_hits_line":null},{"team":"LAA","player":"Meckler, Wade","proj_hits":0.659,"proj_tb":1.107,"proj_hr":0.024,"proj_bb":0.461,"l10_hit_pct":0.8,"vp_pa":null,"vp_h":null,"vp_hr":null,"vp_xwoba":null,"h_streak":null,"hrr_streak":null,"book_hits_line":null},{"team":"LAA","player":"Neto, Zach","proj_hits":0.729,"proj_tb":1.722,"proj_hr":0.257,"proj_bb":0.34,"l10_hit_pct":0.7,"vp_pa":19,"vp_h":4,"vp_hr":0,"vp_xwoba":0.189,"h_streak":null,"hrr_streak":null,"book_hits_line":null},{"team":"LAA","player":"O'Hoppe, Logan","proj_hits":0.606,"proj_tb":1.174,"proj_hr":0.112,"proj_bb":0.148,"l10_hit_pct":0.5,"vp_pa":13,"vp_h":2,"vp_hr":0,"vp_xwoba":0.165,"h_streak":null,"hrr_streak":null,"book_hits_line":null},{"team":"LAA","player":"Peraza, Oswald","proj_hits":0.675,"proj_tb":1.329,"proj_hr":0.038,"proj_bb":0.033,"l10_hit_pct":0.6,"vp_pa":4,"vp_h":1,"vp_hr":0,"vp_xwoba":0.225,"h_streak":null,"hrr_streak":null,"book_hits_line":null},{"team":"LAA","player":"Schanuel, Nolan","proj_hits":0.761,"proj_tb":1.451,"proj_hr":0.133,"proj_bb":0.449,"l10_hit_pct":0.8,"vp_pa":15,"vp_h":4,"vp_hr":0,"vp_xwoba":0.333,"h_streak":null,"hrr_streak":null,"book_hits_line":null},{"team":"LAA","player":"Siri, Jose","proj_hits":0.528,"proj_tb":1.101,"proj_hr":0.143,"proj_bb":0.102,"l10_hit_pct":0.4,"vp_pa":1,"vp_h":0,"vp_hr":0,"vp_xwoba":0.0,"h_streak":null,"hrr_streak":null,"book_hits_line":null},{"team":"LAA","player":"Soler, Jorge","proj_hits":0.709,"proj_tb":1.658,"proj_hr":0.202,"proj_bb":0.479,"l10_hit_pct":0.7,"vp_pa":3,"vp_h":0,"vp_hr":0,"vp_xwoba":0.0,"h_streak":null,"hrr_streak":null,"book_hits_line":null},{"team":"LAA","player":"Walton, Donovan","proj_hits":1.131,"proj_tb":2.464,"proj_hr":0.265,"proj_bb":0.032,"l10_hit_pct":0.9,"vp_pa":null,"vp_h":null,"vp_hr":null,"vp_xwoba":null,"h_streak":null,"hrr_streak":null,"book_hits_line":null}]},{"away_team":"PIT","home_team":"PHI","time":"6:40 PM ET","away_score":null,"home_score":null,"winner":"","lineup_status":"confirmed","batters":[{"team":"PHI","player":"Bohm, Alec","proj_hits":0.75,"proj_tb":1.327,"proj_hr":0.044,"proj_bb":0.287,"l10_hit_pct":0.5,"vp_pa":2,"vp_h":0,"vp_hr":0,"vp_xwoba":0.0,"h_streak":null,"hrr_streak":null,"book_hits_line":null},{"team":"PHI","player":"Crawford, Justin","proj_hits":0.865,"proj_tb":1.432,"proj_hr":0.01,"proj_bb":0.183,"l10_hit_pct":0.7,"vp_pa":1,"vp_h":0,"vp_hr":0,"vp_xwoba":0.0,"h_streak":null,"hrr_streak":null,"book_hits_line":null},{"team":"PHI","player":"Harper, Bryce","proj_hits":1.133,"proj_tb":2.747,"proj_hr":0.334,"proj_bb":0.371,"l10_hit_pct":0.8,"vp_pa":1,"vp_h":1,"vp_hr":1,"vp_xwoba":1.2,"h_streak":null,"hrr_streak":null,"book_hits_line":null},{"team":"PHI","player":"Hill, Derek","proj_hits":0.622,"proj_tb":1.346,"proj_hr":0.169,"proj_bb":0.024,"l10_hit_pct":0.8,"vp_pa":null,"vp_h":null,"vp_hr":null,"vp_xwoba":null,"h_streak":null,"hrr_streak":null,"book_hits_line":null},{"team":"PHI","player":"Marsh, Brandon","proj_hits":1.006,"proj_tb":2.452,"proj_hr":0.309,"proj_bb":0.132,"l10_hit_pct":0.8,"vp_pa":2,"vp_h":0,"vp_hr":0,"vp_xwoba":0.0,"h_streak":null,"hrr_streak":null,"book_hits_line":null},{"team":"PHI","player":"Realmuto, J.T.","proj_hits":0.652,"proj_tb":1.265,"proj_hr":0.03,"proj_bb":0.302,"l10_hit_pct":0.6,"vp_pa":1,"vp_h":0,"vp_hr":0,"vp_xwoba":0.7,"h_streak":null,"hrr_streak":null,"book_hits_line":null},{"team":"PHI","player":"Rincones Jr., Gabriel","proj_hits":0.396,"proj_tb":0.96,"proj_hr":0.126,"proj_bb":0.0,"l10_hit_pct":0.4,"vp_pa":null,"vp_h":null,"vp_hr":null,"vp_xwoba":null,"h_streak":null,"hrr_streak":null,"book_hits_line":null},{"team":"PHI","player":"Schwarber, Kyle","proj_hits":0.882,"proj_tb":2.599,"proj_hr":0.449,"proj_bb":0.506,"l10_hit_pct":0.6,"vp_pa":2,"vp_h":1,"vp_hr":0,"vp_xwoba":0.975,"h_streak":null,"hrr_streak":null,"book_hits_line":null},{"team":"PHI","player":"Sosa, Edmundo","proj_hits":0.641,"proj_tb":1.416,"proj_hr":0.115,"proj_bb":0.013,"l10_hit_pct":0.5,"vp_pa":null,"vp_h":null,"vp_hr":null,"vp_xwoba":null,"h_streak":null,"hrr_streak":null,"book_hits_line":null},{"team":"PHI","player":"Stott, Bryson","proj_hits":0.739,"proj_tb":1.56,"proj_hr":0.113,"proj_bb":0.25,"l10_hit_pct":0.7,"vp_pa":2,"vp_h":0,"vp_hr":0,"vp_xwoba":0.0,"h_streak":null,"hrr_streak":null,"book_hits_line":null},{"team":"PHI","player":"Turner, Trea","proj_hits":1.091,"proj_tb":2.114,"proj_hr":0.13,"proj_bb":0.192,"l10_hit_pct":0.8,"vp_pa":2,"vp_h":1,"vp_hr":0,"vp_xwoba":0.8,"h_streak":null,"hrr_streak":null,"book_hits_line":null},{"team":"PIT","player":"Callihan, Tyler","proj_hits":0.373,"proj_tb":0.886,"proj_hr":0.108,"proj_bb":0.224,"l10_hit_pct":0.3,"vp_pa":null,"vp_h":null,"vp_hr":null,"vp_xwoba":null,"h_streak":null,"hrr_streak":null,"book_hits_line":null},{"team":"PIT","player":"Cook, Billy","proj_hits":0.101,"proj_tb":0.13,"proj_hr":0.0,"proj_bb":0.0,"l10_hit_pct":0.1,"vp_pa":null,"vp_h":null,"vp_hr":null,"vp_xwoba":null,"h_streak":null,"hrr_streak":null,"book_hits_line":null},{"team":"PIT","player":"Davis, Henry","proj_hits":0.353,"proj_tb":1.083,"proj_hr":0.18,"proj_bb":0.218,"l10_hit_pct":0.4,"vp_pa":10,"vp_h":0,"vp_hr":0,"vp_xwoba":0.07,"h_streak":null,"hrr_streak":null,"book_hits_line":null},{"team":"PIT","player":"Gonzales, Nick","proj_hits":0.867,"proj_tb":1.572,"proj_hr":0.085,"proj_bb":0.3,"l10_hit_pct":0.7,"vp_pa":11,"vp_h":3,"vp_hr":0,"vp_xwoba":0.309,"h_streak":null,"hrr_streak":null,"book_hits_line":null},{"team":"PIT","player":"Griffin, Konnor","proj_hits":0.812,"proj_tb":1.691,"proj_hr":0.167,"proj_bb":0.252,"l10_hit_pct":0.7,"vp_pa":4,"vp_h":2,"vp_hr":0,"vp_xwoba":0.538,"h_streak":null,"hrr_streak":null,"book_hits_line":null},{"team":"PIT","player":"Lowe, Brandon","proj_hits":0.81,"proj_tb":2.132,"proj_hr":0.281,"proj_bb":0.195,"l10_hit_pct":0.7,"vp_pa":5,"vp_h":0,"vp_hr":0,"vp_xwoba":0.0,"h_streak":null,"hrr_streak":null,"book_hits_line":null},{"team":"PIT","player":"Mangum, Jake","proj_hits":0.819,"proj_tb":1.319,"proj_hr":0.005,"proj_bb":0.104,"l10_hit_pct":0.7,"vp_pa":null,"vp_h":null,"vp_hr":null,"vp_xwoba":null,"h_streak":null,"hrr_streak":null,"book_hits_line":null},{"team":"PIT","player":"O'Hearn, Ryan","proj_hits":0.892,"proj_tb":1.883,"proj_hr":0.2,"proj_bb":0.158,"l10_hit_pct":0.6,"vp_pa":1,"vp_h":0,"vp_hr":0,"vp_xwoba":0.0,"h_streak":null,"hrr_streak":null,"book_hits_line":null},{"team":"PIT","player":"Ozuna, Marcell","proj_hits":0.672,"proj_tb":1.401,"proj_hr":0.178,"proj_bb":0.317,"l10_hit_pct":0.7,"vp_pa":17,"vp_h":5,"vp_hr":0,"vp_xwoba":0.308,"h_streak":null,"hrr_streak":null,"book_hits_line":null},{"team":"PIT","player":"Reynolds, Bryan","proj_hits":0.844,"proj_tb":1.741,"proj_hr":0.141,"proj_bb":0.584,"l10_hit_pct":0.9,"vp_pa":16,"vp_h":6,"vp_hr":0,"vp_xwoba":0.403,"h_streak":null,"hrr_streak":null,"book_hits_line":null},{"team":"PIT","player":"Triolo, Jared","proj_hits":0.678,"proj_tb":1.319,"proj_hr":0.074,"proj_bb":0.217,"l10_hit_pct":0.6,"vp_pa":11,"vp_h":3,"vp_hr":0,"vp_xwoba":0.341,"h_streak":null,"hrr_streak":null,"book_hits_line":null},{"team":"PIT","player":"Valdez, Esmerlyn","proj_hits":0.67,"proj_tb":2.31,"proj_hr":0.42,"proj_bb":0.293,"l10_hit_pct":0.6,"vp_pa":null,"vp_h":null,"vp_hr":null,"vp_xwoba":null,"h_streak":null,"hrr_streak":null,"book_hits_line":null}]},{"away_team":"DET","home_team":"NYY","time":"7:05 PM ET","away_score":null,"home_score":null,"winner":"","lineup_status":"confirmed","batters":[{"team":"NYY","player":"Bellinger, Cody","proj_hits":0.713,"proj_tb":1.171,"proj_hr":0.052,"proj_bb":0.51,"l10_hit_pct":0.4,"vp_pa":6,"vp_h":1,"vp_hr":0,"vp_xwoba":0.15,"h_streak":null,"hrr_streak":null,"book_hits_line":null},{"team":"NYY","player":"Chisholm Jr., Jazz","proj_hits":0.528,"proj_tb":1.089,"proj_hr":0.129,"proj_bb":0.2,"l10_hit_pct":0.4,"vp_pa":5,"vp_h":0,"vp_hr":0,"vp_xwoba":0.0,"h_streak":null,"hrr_streak":null,"book_hits_line":null},{"team":"NYY","player":"Goldschmidt, Paul","proj_hits":0.669,"proj_tb":1.919,"proj_hr":0.307,"proj_bb":0.212,"l10_hit_pct":0.5,"vp_pa":13,"vp_h":7,"vp_hr":4,"vp_xwoba":0.814,"h_streak":null,"hrr_streak":null,"book_hits_line":null},{"team":"NYY","player":"Jones, Spencer","proj_hits":0.523,"proj_tb":1.335,"proj_hr":0.111,"proj_bb":0.342,"l10_hit_pct":0.5,"vp_pa":null,"vp_h":null,"vp_hr":null,"vp_xwoba":null,"h_streak":null,"hrr_streak":null,"book_hits_line":null},{"team":"NYY","player":"Rice, Ben","proj_hits":0.56,"proj_tb":1.457,"proj_hr":0.201,"proj_bb":0.219,"l10_hit_pct":0.2,"vp_pa":6,"vp_h":2,"vp_hr":0,"vp_xwoba":0.3,"h_streak":null,"hrr_streak":null,"book_hits_line":null},{"team":"NYY","player":"Rosario, Amed","proj_hits":0.616,"proj_tb":1.586,"proj_hr":0.241,"proj_bb":0.186,"l10_hit_pct":0.7,"vp_pa":15,"vp_h":1,"vp_hr":0,"vp_xwoba":0.153,"h_streak":null,"hrr_streak":null,"book_hits_line":null},{"team":"NYY","player":"Schuemann, Max","proj_hits":0.293,"proj_tb":0.788,"proj_hr":0.083,"proj_bb":0.174,"l10_hit_pct":0.3,"vp_pa":4,"vp_h":0,"vp_hr":0,"vp_xwoba":0.0,"h_streak":null,"hrr_streak":null,"book_hits_line":null},{"team":"NYY","player":"Volpe, Anthony","proj_hits":0.479,"proj_tb":0.81,"proj_hr":0.007,"proj_bb":0.393,"l10_hit_pct":0.4,"vp_pa":12,"vp_h":0,"vp_hr":0,"vp_xwoba":0.0,"h_streak":null,"hrr_streak":null,"book_hits_line":null},{"team":"NYY","player":"Wells, Austin","proj_hits":0.254,"proj_tb":0.512,"proj_hr":0.028,"proj_bb":0.121,"l10_hit_pct":0.2,"vp_pa":4,"vp_h":0,"vp_hr":0,"vp_xwoba":0.0,"h_streak":null,"hrr_streak":null,"book_hits_line":null},{"team":"DET","player":"Carpenter, Kerry","proj_hits":0.538,"proj_tb":1.537,"proj_hr":0.202,"proj_bb":0.251,"l10_hit_pct":0.5,"vp_pa":3,"vp_h":0,"vp_hr":0,"vp_xwoba":0.233,"h_streak":null,"hrr_streak":null,"book_hits_line":null},{"team":"DET","player":"Dingler, Dillon","proj_hits":0.88,"proj_tb":2.435,"proj_hr":0.321,"proj_bb":0.179,"l10_hit_pct":0.6,"vp_pa":2,"vp_h":1,"vp_hr":0,"vp_xwoba":0.45,"h_streak":null,"hrr_streak":null,"book_hits_line":null},{"team":"DET","player":"Greene, Riley","proj_hits":0.839,"proj_tb":1.708,"proj_hr":0.133,"proj_bb":0.539,"l10_hit_pct":0.5,"vp_pa":3,"vp_h":0,"vp_hr":0,"vp_xwoba":0.0,"h_streak":null,"hrr_streak":null,"book_hits_line":null},{"team":"DET","player":"Jones, Jahmai","proj_hits":0.195,"proj_tb":0.344,"proj_hr":0.015,"proj_bb":0.052,"l10_hit_pct":0.2,"vp_pa":null,"vp_h":null,"vp_hr":null,"vp_xwoba":null,"h_streak":null,"hrr_streak":null,"book_hits_line":null},{"team":"DET","player":"Keith, Colt","proj_hits":0.645,"proj_tb":1.149,"proj_hr":0.105,"proj_bb":0.134,"l10_hit_pct":0.4,"vp_pa":3,"vp_h":1,"vp_hr":0,"vp_xwoba":0.3,"h_streak":null,"hrr_streak":null,"book_hits_line":null},{"team":"DET","player":"Lee, Hao-Yu","proj_hits":0.842,"proj_tb":1.714,"proj_hr":0.107,"proj_bb":0.17,"l10_hit_pct":0.8,"vp_pa":null,"vp_h":null,"vp_hr":null,"vp_xwoba":null,"h_streak":null,"hrr_streak":null,"book_hits_line":null},{"team":"DET","player":"Malgeri, Ben","proj_hits":0.608,"proj_tb":0.8,"proj_hr":0.0,"proj_bb":0.0,"l10_hit_pct":null,"vp_pa":null,"vp_h":null,"vp_hr":null,"vp_xwoba":null,"h_streak":null,"hrr_streak":null,"book_hits_line":null},{"team":"DET","player":"McGonigle, Kevin","proj_hits":1.016,"proj_tb":1.799,"proj_hr":0.029,"proj_bb":0.805,"l10_hit_pct":0.8,"vp_pa":null,"vp_h":null,"vp_hr":null,"vp_xwoba":null,"h_streak":null,"hrr_streak":null,"book_hits_line":null},{"team":"DET","player":"McKinstry, Zach","proj_hits":0.703,"proj_tb":1.5,"proj_hr":0.086,"proj_bb":0.359,"l10_hit_pct":0.7,"vp_pa":null,"vp_h":null,"vp_hr":null,"vp_xwoba":null,"h_streak":null,"hrr_streak":null,"book_hits_line":null},{"team":"DET","player":"Outman, James","proj_hits":0.35,"proj_tb":0.791,"proj_hr":0.094,"proj_bb":0.267,"l10_hit_pct":0.4,"vp_pa":2,"vp_h":1,"vp_hr":1,"vp_xwoba":1.0,"h_streak":null,"hrr_streak":null,"book_hits_line":null},{"team":"DET","player":"Rogers, Jake","proj_hits":0.371,"proj_tb":0.86,"proj_hr":0.091,"proj_bb":0.345,"l10_hit_pct":0.3,"vp_pa":null,"vp_h":null,"vp_hr":null,"vp_xwoba":null,"h_streak":null,"hrr_streak":null,"book_hits_line":null},{"team":"DET","player":"Torkelson, Spencer","proj_hits":0.754,"proj_tb":1.821,"proj_hr":0.135,"proj_bb":0.515,"l10_hit_pct":0.7,"vp_pa":3,"vp_h":0,"vp_hr":0,"vp_xwoba":0.0,"h_streak":null,"hrr_streak":null,"book_hits_line":null},{"team":"DET","player":"Vierling, Matt","proj_hits":0.652,"proj_tb":1.31,"proj_hr":0.085,"proj_bb":0.172,"l10_hit_pct":0.7,"vp_pa":null,"vp_h":null,"vp_hr":null,"vp_xwoba":null,"h_streak":null,"hrr_streak":null,"book_hits_line":null}]},{"away_team":"CIN","home_team":"MIL","time":"7:40 PM ET","away_score":null,"home_score":null,"winner":"","lineup_status":"confirmed","batters":[{"team":"MIL","player":"Bauers, Jake","proj_hits":0.66,"proj_tb":1.17,"proj_hr":0.123,"proj_bb":0.515,"l10_hit_pct":0.5,"vp_pa":5,"vp_h":2,"vp_hr":1,"vp_xwoba":0.58,"h_streak":null,"hrr_streak":null,"book_hits_line":null},{"team":"MIL","player":"Chourio, Jackson","proj_hits":1.068,"proj_tb":1.957,"proj_hr":0.18,"proj_bb":0.345,"l10_hit_pct":0.8,"vp_pa":3,"vp_h":1,"vp_hr":0,"vp_xwoba":0.3,"h_streak":null,"hrr_streak":null,"book_hits_line":null},{"team":"MIL","player":"Contreras, William","proj_hits":1.034,"proj_tb":1.689,"proj_hr":0.181,"proj_bb":0.444,"l10_hit_pct":0.5,"vp_pa":5,"vp_h":3,"vp_hr":1,"vp_xwoba":0.76,"h_streak":null,"hrr_streak":null,"book_hits_line":null},{"team":"MIL","player":"Frelick, Sal","proj_hits":0.891,"proj_tb":1.273,"proj_hr":0.016,"proj_bb":0.254,"l10_hit_pct":0.7,"vp_pa":5,"vp_h":2,"vp_hr":0,"vp_xwoba":0.43,"h_streak":null,"hrr_streak":null,"book_hits_line":null},{"team":"MIL","player":"Hamilton, David","proj_hits":0.646,"proj_tb":0.918,"proj_hr":0.017,"proj_bb":0.105,"l10_hit_pct":0.5,"vp_pa":3,"vp_h":0,"vp_hr":0,"vp_xwoba":0.0,"h_streak":null,"hrr_streak":null,"book_hits_line":null},{"team":"MIL","player":"Mitchell, Garrett","proj_hits":0.706,"proj_tb":1.238,"proj_hr":0.106,"proj_bb":0.357,"l10_hit_pct":0.4,"vp_pa":5,"vp_h":1,"vp_hr":0,"vp_xwoba":0.46,"h_streak":null,"hrr_streak":null,"book_hits_line":null},{"team":"MIL","player":"Ortiz, Joey","proj_hits":0.596,"proj_tb":0.917,"proj_hr":0.074,"proj_bb":0.113,"l10_hit_pct":0.5,"vp_pa":null,"vp_h":null,"vp_hr":null,"vp_xwoba":null,"h_streak":null,"hrr_streak":null,"book_hits_line":null},{"team":"MIL","player":"Perkins, Blake","proj_hits":0.559,"proj_tb":0.922,"proj_hr":0.065,"proj_bb":0.208,"l10_hit_pct":0.7,"vp_pa":2,"vp_h":0,"vp_hr":0,"vp_xwoba":0.35,"h_streak":null,"hrr_streak":null,"book_hits_line":null},{"team":"MIL","player":"Pratt, Cooper","proj_hits":0.549,"proj_tb":0.662,"proj_hr":0.0,"proj_bb":0.402,"l10_hit_pct":0.4,"vp_pa":2,"vp_h":0,"vp_hr":0,"vp_xwoba":0.0,"h_streak":null,"hrr_streak":null,"book_hits_line":null},{"team":"MIL","player":"Turang, Brice","proj_hits":1.09,"proj_tb":1.836,"proj_hr":0.127,"proj_bb":0.217,"l10_hit_pct":0.7,"vp_pa":5,"vp_h":0,"vp_hr":0,"vp_xwoba":0.28,"h_streak":null,"hrr_streak":null,"book_hits_line":null},{"team":"MIL","player":"Vaughn, Andrew","proj_hits":0.722,"proj_tb":1.192,"proj_hr":0.014,"proj_bb":0.485,"l10_hit_pct":0.5,"vp_pa":null,"vp_h":null,"vp_hr":null,"vp_xwoba":null,"h_streak":null,"hrr_streak":null,"book_hits_line":null},{"team":"MIL","player":"Yelich, Christian","proj_hits":1.027,"proj_tb":1.669,"proj_hr":0.123,"proj_bb":0.428,"l10_hit_pct":0.5,"vp_pa":3,"vp_h":0,"vp_hr":0,"vp_xwoba":0.233,"h_streak":null,"hrr_streak":null,"book_hits_line":null},{"team":"CIN","player":"Arroyo, Edwin","proj_hits":1.193,"proj_tb":1.652,"proj_hr":0.0,"proj_bb":0.126,"l10_hit_pct":0.6,"vp_pa":null,"vp_h":null,"vp_hr":null,"vp_xwoba":null,"h_streak":null,"hrr_streak":null,"book_hits_line":null},{"team":"CIN","player":"Bleday, JJ","proj_hits":0.678,"proj_tb":1.164,"proj_hr":0.092,"proj_bb":0.574,"l10_hit_pct":0.4,"vp_pa":null,"vp_h":null,"vp_hr":null,"vp_xwoba":null,"h_streak":null,"hrr_streak":null,"book_hits_line":null},{"team":"CIN","player":"De La Cruz, Elly","proj_hits":0.902,"proj_tb":1.757,"proj_hr":0.17,"proj_bb":0.457,"l10_hit_pct":0.5,"vp_pa":3,"vp_h":1,"vp_hr":0,"vp_xwoba":0.417,"h_streak":null,"hrr_streak":null,"book_hits_line":null},{"team":"CIN","player":"Lowe, Nathaniel","proj_hits":0.596,"proj_tb":1.134,"proj_hr":0.056,"proj_bb":0.251,"l10_hit_pct":0.5,"vp_pa":null,"vp_h":null,"vp_hr":null,"vp_xwoba":null,"h_streak":null,"hrr_streak":null,"book_hits_line":null},{"team":"CIN","player":"Marte, Noelvi","proj_hits":0.844,"proj_tb":1.532,"proj_hr":0.106,"proj_bb":0.3,"l10_hit_pct":0.5,"vp_pa":3,"vp_h":1,"vp_hr":0,"vp_xwoba":0.533,"h_streak":null,"hrr_streak":null,"book_hits_line":null},{"team":"CIN","player":"McLain, Matt","proj_hits":0.556,"proj_tb":0.914,"proj_hr":0.038,"proj_bb":0.462,"l10_hit_pct":0.4,"vp_pa":2,"vp_h":0,"vp_hr":0,"vp_xwoba":0.0,"h_streak":null,"hrr_streak":null,"book_hits_line":null},{"team":"CIN","player":"Steer, Spencer","proj_hits":0.874,"proj_tb":1.751,"proj_hr":0.186,"proj_bb":0.127,"l10_hit_pct":0.6,"vp_pa":null,"vp_h":null,"vp_hr":null,"vp_xwoba":null,"h_streak":null,"hrr_streak":null,"book_hits_line":null},{"team":"CIN","player":"Stephenson, Tyler","proj_hits":0.868,"proj_tb":1.619,"proj_hr":0.128,"proj_bb":0.362,"l10_hit_pct":0.7,"vp_pa":2,"vp_h":0,"vp_hr":0,"vp_xwoba":0.35,"h_streak":null,"hrr_streak":null,"book_hits_line":null},{"team":"CIN","player":"Stewart, Sal","proj_hits":1.089,"proj_tb":2.125,"proj_hr":0.161,"proj_bb":0.243,"l10_hit_pct":0.7,"vp_pa":3,"vp_h":0,"vp_hr":0,"vp_xwoba":0.0,"h_streak":null,"hrr_streak":null,"book_hits_line":null},{"team":"CIN","player":"Trevino, Jose","proj_hits":0.725,"proj_tb":1.049,"proj_hr":0.003,"proj_bb":0.024,"l10_hit_pct":0.6,"vp_pa":null,"vp_h":null,"vp_hr":null,"vp_xwoba":null,"h_streak":null,"hrr_streak":null,"book_hits_line":null}]},{"away_team":"TB","home_team":"KC","time":"7:40 PM ET","away_score":null,"home_score":null,"winner":"","lineup_status":"confirmed","batters":[{"team":"KC","player":"Caglianone, Jac","proj_hits":0.967,"proj_tb":2.757,"proj_hr":0.455,"proj_bb":0.347,"l10_hit_pct":0.6,"vp_pa":3,"vp_h":0,"vp_hr":0,"vp_xwoba":0.3,"h_streak":null,"hrr_streak":null,"book_hits_line":null},{"team":"KC","player":"Collins, Isaac","proj_hits":0.911,"proj_tb":1.614,"proj_hr":0.016,"proj_bb":0.322,"l10_hit_pct":0.8,"vp_pa":3,"vp_h":1,"vp_hr":0,"vp_xwoba":0.3,"h_streak":null,"hrr_streak":null,"book_hits_line":null},{"team":"KC","player":"Jensen, Carter","proj_hits":1.095,"proj_tb":2.175,"proj_hr":0.176,"proj_bb":0.416,"l10_hit_pct":1.0,"vp_pa":3,"vp_h":1,"vp_hr":0,"vp_xwoba":0.533,"h_streak":null,"hrr_streak":null,"book_hits_line":null},{"team":"KC","player":"Loftin, Nick","proj_hits":0.741,"proj_tb":1.658,"proj_hr":0.153,"proj_bb":0.281,"l10_hit_pct":0.4,"vp_pa":4,"vp_h":0,"vp_hr":0,"vp_xwoba":0.175,"h_streak":null,"hrr_streak":null,"book_hits_line":null},{"team":"KC","player":"Marte, Starling","proj_hits":0.824,"proj_tb":1.333,"proj_hr":0.075,"proj_bb":0.351,"l10_hit_pct":0.6,"vp_pa":1,"vp_h":0,"vp_hr":0,"vp_xwoba":0.0,"h_streak":null,"hrr_streak":null,"book_hits_line":null},{"team":"KC","player":"Massey, Michael","proj_hits":0.943,"proj_tb":1.819,"proj_hr":0.122,"proj_bb":0.316,"l10_hit_pct":0.6,"vp_pa":9,"vp_h":2,"vp_hr":0,"vp_xwoba":0.239,"h_streak":null,"hrr_streak":null,"book_hits_line":null},{"team":"KC","player":"Misner, Kameron","proj_hits":1.173,"proj_tb":1.513,"proj_hr":0.013,"proj_bb":0.146,"l10_hit_pct":0.8,"vp_pa":2,"vp_h":0,"vp_hr":0,"vp_xwoba":0.0,"h_streak":null,"hrr_streak":null,"book_hits_line":null},{"team":"KC","player":"Perez, Salvador","proj_hits":0.831,"proj_tb":1.543,"proj_hr":0.111,"proj_bb":0.052,"l10_hit_pct":0.6,"vp_pa":22,"vp_h":2,"vp_hr":0,"vp_xwoba":0.202,"h_streak":null,"hrr_streak":null,"book_hits_line":null},{"team":"KC","player":"Rave, John","proj_hits":0.516,"proj_tb":1.316,"proj_hr":0.11,"proj_bb":0.339,"l10_hit_pct":0.4,"vp_pa":2,"vp_h":1,"vp_hr":0,"vp_xwoba":0.625,"h_streak":null,"hrr_streak":null,"book_hits_line":null},{"team":"KC","player":"Rojas, Josh","proj_hits":0.579,"proj_tb":1.111,"proj_hr":0.095,"proj_bb":0.096,"l10_hit_pct":0.5,"vp_pa":1,"vp_h":1,"vp_hr":0,"vp_xwoba":0.9,"h_streak":null,"hrr_streak":null,"book_hits_line":null},{"team":"KC","player":"Thomas, Lane","proj_hits":0.659,"proj_tb":1.208,"proj_hr":0.03,"proj_bb":0.229,"l10_hit_pct":0.5,"vp_pa":2,"vp_h":1,"vp_hr":0,"vp_xwoba":0.45,"h_streak":null,"hrr_streak":null,"book_hits_line":null},{"team":"KC","player":"Tolbert, Tyler","proj_hits":0.44,"proj_tb":0.534,"proj_hr":0.002,"proj_bb":0.342,"l10_hit_pct":0.5,"vp_pa":2,"vp_h":0,"vp_hr":0,"vp_xwoba":0.35,"h_streak":null,"hrr_streak":null,"book_hits_line":null},{"team":"KC","player":"Witt Jr., Bobby","proj_hits":1.236,"proj_tb":2.425,"proj_hr":0.14,"proj_bb":0.559,"l10_hit_pct":0.7,"vp_pa":18,"vp_h":3,"vp_hr":0,"vp_xwoba":0.394,"h_streak":null,"hrr_streak":null,"book_hits_line":null},{"team":"TB","player":"Aranda, Jonathan","proj_hits":1.284,"proj_tb":2.156,"proj_hr":0.174,"proj_bb":0.49,"l10_hit_pct":0.9,"vp_pa":3,"vp_h":2,"vp_hr":0,"vp_xwoba":0.717,"h_streak":null,"hrr_streak":null,"book_hits_line":null},{"team":"TB","player":"Caminero, Junior","proj_hits":1.44,"proj_tb":3.106,"proj_hr":0.549,"proj_bb":0.519,"l10_hit_pct":0.7,"vp_pa":5,"vp_h":0,"vp_hr":0,"vp_xwoba":0.183,"h_streak":null,"hrr_streak":null,"book_hits_line":null},{"team":"TB","player":"DeLuca, Jonny","proj_hits":1.041,"proj_tb":1.965,"proj_hr":0.174,"proj_bb":0.123,"l10_hit_pct":0.7,"vp_pa":2,"vp_h":1,"vp_hr":0,"vp_xwoba":0.483,"h_streak":null,"hrr_streak":null,"book_hits_line":null},{"team":"TB","player":"Feduccia, Hunter","proj_hits":0.577,"proj_tb":0.767,"proj_hr":0.007,"proj_bb":0.205,"l10_hit_pct":0.4,"vp_pa":null,"vp_h":null,"vp_hr":null,"vp_xwoba":null,"h_streak":null,"hrr_streak":null,"book_hits_line":null},{"team":"TB","player":"Fortes, Nick","proj_hits":0.932,"proj_tb":1.232,"proj_hr":0.007,"proj_bb":0.104,"l10_hit_pct":0.5,"vp_pa":3,"vp_h":1,"vp_hr":0,"vp_xwoba":0.533,"h_streak":null,"hrr_streak":null,"book_hits_line":null},{"team":"TB","player":"Mesa Jr., Victor","proj_hits":0.815,"proj_tb":1.637,"proj_hr":0.24,"proj_bb":0.431,"l10_hit_pct":0.5,"vp_pa":null,"vp_h":null,"vp_hr":null,"vp_xwoba":null,"h_streak":null,"hrr_streak":null,"book_hits_line":null},{"team":"TB","player":"Mullins, Cedric","proj_hits":0.843,"proj_tb":1.363,"proj_hr":0.146,"proj_bb":0.241,"l10_hit_pct":0.8,"vp_pa":null,"vp_h":null,"vp_hr":null,"vp_xwoba":null,"h_streak":null,"hrr_streak":null,"book_hits_line":null},{"team":"TB","player":"Palacios, Richie","proj_hits":0.804,"proj_tb":1.114,"proj_hr":0.007,"proj_bb":0.315,"l10_hit_pct":0.6,"vp_pa":null,"vp_h":null,"vp_hr":null,"vp_xwoba":null,"h_streak":null,"hrr_streak":null,"book_hits_line":null},{"team":"TB","player":"Simpson, Chandler","proj_hits":1.189,"proj_tb":1.542,"proj_hr":0.0,"proj_bb":0.261,"l10_hit_pct":0.8,"vp_pa":5,"vp_h":1,"vp_hr":0,"vp_xwoba":0.183,"h_streak":null,"hrr_streak":null,"book_hits_line":null},{"team":"TB","player":"Vilade, Ryan","proj_hits":0.881,"proj_tb":1.608,"proj_hr":0.167,"proj_bb":0.215,"l10_hit_pct":0.5,"vp_pa":5,"vp_h":0,"vp_hr":0,"vp_xwoba":0.0,"h_streak":null,"hrr_streak":null,"book_hits_line":null},{"team":"TB","player":"Walls, Taylor","proj_hits":0.766,"proj_tb":1.04,"proj_hr":0.0,"proj_bb":0.424,"l10_hit_pct":0.8,"vp_pa":5,"vp_h":1,"vp_hr":0,"vp_xwoba":0.25,"h_streak":null,"hrr_streak":null,"book_hits_line":null},{"team":"TB","player":"Williamson, Ben","proj_hits":0.747,"proj_tb":1.322,"proj_hr":0.145,"proj_bb":0.171,"l10_hit_pct":0.5,"vp_pa":5,"vp_h":0,"vp_hr":0,"vp_xwoba":0.28,"h_streak":null,"hrr_streak":null,"book_hits_line":null}]},{"away_team":"MIN","home_team":"HOU","time":"8:10 PM ET","away_score":null,"home_score":null,"winner":"","lineup_status":"confirmed","batters":[{"team":"HOU","player":"Altuve, Jose","proj_hits":0.949,"proj_tb":2.032,"proj_hr":0.141,"proj_bb":0.236,"l10_hit_pct":0.6,"vp_pa":15,"vp_h":2,"vp_hr":0,"vp_xwoba":0.167,"h_streak":null,"hrr_streak":null,"book_hits_line":null},{"team":"HOU","player":"Alvarez, Yordan","proj_hits":0.893,"proj_tb":1.668,"proj_hr":0.206,"proj_bb":0.888,"l10_hit_pct":0.4,"vp_pa":16,"vp_h":4,"vp_hr":3,"vp_xwoba":0.519,"h_streak":null,"hrr_streak":null,"book_hits_line":null},{"team":"HOU","player":"Delgado, Raynel","proj_hits":0.799,"proj_tb":1.5,"proj_hr":0.15,"proj_bb":0.0,"l10_hit_pct":0.625,"vp_pa":null,"vp_h":null,"vp_hr":null,"vp_xwoba":null,"h_streak":null,"hrr_streak":null,"book_hits_line":null},{"team":"HOU","player":"Diaz, Yainer","proj_hits":0.78,"proj_tb":1.585,"proj_hr":0.111,"proj_bb":0.173,"l10_hit_pct":0.7,"vp_pa":6,"vp_h":3,"vp_hr":1,"vp_xwoba":0.692,"h_streak":null,"hrr_streak":null,"book_hits_line":null},{"team":"HOU","player":"Loperfido, Joey","proj_hits":0.427,"proj_tb":1.096,"proj_hr":0.075,"proj_bb":0.2,"l10_hit_pct":0.3,"vp_pa":2,"vp_h":0,"vp_hr":0,"vp_xwoba":0.0,"h_streak":null,"hrr_streak":null,"book_hits_line":null},{"team":"HOU","player":"Meyers, Jake","proj_hits":0.606,"proj_tb":0.946,"proj_hr":0.017,"proj_bb":0.233,"l10_hit_pct":0.4,"vp_pa":10,"vp_h":0,"vp_hr":0,"vp_xwoba":0.191,"h_streak":null,"hrr_streak":null,"book_hits_line":null},{"team":"HOU","player":"Paredes, Isaac","proj_hits":0.981,"proj_tb":2.041,"proj_hr":0.145,"proj_bb":0.346,"l10_hit_pct":0.8,"vp_pa":12,"vp_h":3,"vp_hr":1,"vp_xwoba":0.375,"h_streak":null,"hrr_streak":null,"book_hits_line":null},{"team":"HOU","player":"Smith, Cam","proj_hits":0.603,"proj_tb":1.748,"proj_hr":0.307,"proj_bb":0.248,"l10_hit_pct":0.5,"vp_pa":5,"vp_h":0,"vp_hr":0,"vp_xwoba":0.0,"h_streak":null,"hrr_streak":null,"book_hits_line":null},{"team":"HOU","player":"Trammell, Taylor","proj_hits":0.549,"proj_tb":1.486,"proj_hr":0.227,"proj_bb":0.176,"l10_hit_pct":0.3,"vp_pa":2,"vp_h":0,"vp_hr":0,"vp_xwoba":0.0,"h_streak":null,"hrr_streak":null,"book_hits_line":null},{"team":"HOU","player":"Walker, Christian","proj_hits":0.7,"proj_tb":1.732,"proj_hr":0.174,"proj_bb":0.338,"l10_hit_pct":0.4,"vp_pa":8,"vp_h":2,"vp_hr":1,"vp_xwoba":0.45,"h_streak":null,"hrr_streak":null,"book_hits_line":null},{"team":"MIN","player":"Bell, Josh","proj_hits":0.901,"proj_tb":1.933,"proj_hr":0.199,"proj_bb":0.282,"l10_hit_pct":0.7,"vp_pa":null,"vp_h":null,"vp_hr":null,"vp_xwoba":null,"h_streak":null,"hrr_streak":null,"book_hits_line":null},{"team":"MIN","player":"Buxton, Byron","proj_hits":1.088,"proj_tb":2.241,"proj_hr":0.261,"proj_bb":0.15,"l10_hit_pct":0.6,"vp_pa":2,"vp_h":2,"vp_hr":0,"vp_xwoba":1.25,"h_streak":null,"hrr_streak":null,"book_hits_line":null},{"team":"MIN","player":"Caratini, Victor","proj_hits":1.019,"proj_tb":2.097,"proj_hr":0.302,"proj_bb":0.532,"l10_hit_pct":0.8,"vp_pa":2,"vp_h":1,"vp_hr":0,"vp_xwoba":0.625,"h_streak":null,"hrr_streak":null,"book_hits_line":null},{"team":"MIN","player":"Clemens, Kody","proj_hits":0.767,"proj_tb":1.732,"proj_hr":0.223,"proj_bb":0.251,"l10_hit_pct":0.6,"vp_pa":1,"vp_h":1,"vp_hr":1,"vp_xwoba":2.0,"h_streak":null,"hrr_streak":null,"book_hits_line":null},{"team":"MIN","player":"Fedko, Kyler","proj_hits":0.0,"proj_tb":0.0,"proj_hr":0.0,"proj_bb":0.457,"l10_hit_pct":null,"vp_pa":null,"vp_h":null,"vp_hr":null,"vp_xwoba":null,"h_streak":null,"hrr_streak":null,"book_hits_line":null},{"team":"MIN","player":"Gray, Tristan","proj_hits":0.615,"proj_tb":0.944,"proj_hr":0.03,"proj_bb":0.166,"l10_hit_pct":0.4,"vp_pa":null,"vp_h":null,"vp_hr":null,"vp_xwoba":null,"h_streak":null,"hrr_streak":null,"book_hits_line":null},{"team":"MIN","player":"Keaschall, Luke","proj_hits":0.876,"proj_tb":0.98,"proj_hr":0.007,"proj_bb":0.376,"l10_hit_pct":0.4,"vp_pa":null,"vp_h":null,"vp_hr":null,"vp_xwoba":null,"h_streak":null,"hrr_streak":null,"book_hits_line":null},{"team":"MIN","player":"Kreidler, Ryan","proj_hits":1.019,"proj_tb":1.836,"proj_hr":0.173,"proj_bb":0.127,"l10_hit_pct":0.8,"vp_pa":null,"vp_h":null,"vp_hr":null,"vp_xwoba":null,"h_streak":null,"hrr_streak":null,"book_hits_line":null},{"team":"MIN","player":"Larnach, Trevor","proj_hits":1.12,"proj_tb":2.055,"proj_hr":0.12,"proj_bb":0.241,"l10_hit_pct":0.8,"vp_pa":2,"vp_h":0,"vp_hr":0,"vp_xwoba":0.35,"h_streak":null,"hrr_streak":null,"book_hits_line":null},{"team":"MIN","player":"Lee, Brooks","proj_hits":1.296,"proj_tb":2.613,"proj_hr":0.251,"proj_bb":0.262,"l10_hit_pct":0.7,"vp_pa":1,"vp_h":0,"vp_hr":0,"vp_xwoba":0.0,"h_streak":null,"hrr_streak":null,"book_hits_line":null},{"team":"MIN","player":"Lewis, Royce","proj_hits":0.974,"proj_tb":2.113,"proj_hr":0.242,"proj_bb":0.222,"l10_hit_pct":0.9,"vp_pa":1,"vp_h":0,"vp_hr":0,"vp_xwoba":0.7,"h_streak":null,"hrr_streak":null,"book_hits_line":null},{"team":"MIN","player":"Martin, Austin","proj_hits":0.796,"proj_tb":1.044,"proj_hr":0.012,"proj_bb":0.19,"l10_hit_pct":0.6,"vp_pa":null,"vp_h":null,"vp_hr":null,"vp_xwoba":null,"h_streak":null,"hrr_streak":null,"book_hits_line":null}]},{"away_team":"MIA","home_team":"COL","time":"8:40 PM ET","away_score":null,"home_score":null,"winner":"","lineup_status":"projected","batters":[{"team":"COL","player":"Carrigg, Cole","proj_hits":0.9,"proj_tb":1.742,"proj_hr":0.065,"proj_bb":0.565,"l10_hit_pct":0.7,"vp_pa":null,"vp_h":null,"vp_hr":null,"vp_xwoba":null,"h_streak":null,"hrr_streak":null,"book_hits_line":null},{"team":"COL","player":"Castro, Willi","proj_hits":0.949,"proj_tb":1.73,"proj_hr":0.096,"proj_bb":0.257,"l10_hit_pct":0.7,"vp_pa":6,"vp_h":1,"vp_hr":0,"vp_xwoba":0.267,"h_streak":null,"hrr_streak":null,"book_hits_line":null},{"team":"COL","player":"Freeman, Tyler","proj_hits":1.116,"proj_tb":1.592,"proj_hr":0.02,"proj_bb":0.052,"l10_hit_pct":0.7,"vp_pa":2,"vp_h":0,"vp_hr":0,"vp_xwoba":0.0,"h_streak":null,"hrr_streak":null,"book_hits_line":null},{"team":"COL","player":"Fulford, Braxton","proj_hits":0.39,"proj_tb":0.806,"proj_hr":0.013,"proj_bb":0.345,"l10_hit_pct":0.5,"vp_pa":null,"vp_h":null,"vp_hr":null,"vp_xwoba":null,"h_streak":null,"hrr_streak":null,"book_hits_line":null},{"team":"COL","player":"Goodman, Hunter","proj_hits":0.879,"proj_tb":2.701,"proj_hr":0.41,"proj_bb":0.19,"l10_hit_pct":0.5,"vp_pa":5,"vp_h":0,"vp_hr":0,"vp_xwoba":0.18,"h_streak":null,"hrr_streak":null,"book_hits_line":null},{"team":"COL","player":"Johnston, Troy","proj_hits":0.805,"proj_tb":1.201,"proj_hr":0.015,"proj_bb":0.431,"l10_hit_pct":0.4,"vp_pa":3,"vp_h":1,"vp_hr":0,"vp_xwoba":0.3,"h_streak":null,"hrr_streak":null,"book_hits_line":null},{"team":"COL","player":"Julien, Edouard","proj_hits":0.647,"proj_tb":1.067,"proj_hr":0.009,"proj_bb":0.581,"l10_hit_pct":0.6,"vp_pa":3,"vp_h":1,"vp_hr":0,"vp_xwoba":0.417,"h_streak":null,"hrr_streak":null,"book_hits_line":null},{"team":"COL","player":"Karros, Kyle","proj_hits":0.758,"proj_tb":1.735,"proj_hr":0.153,"proj_bb":0.293,"l10_hit_pct":0.7,"vp_pa":5,"vp_h":0,"vp_hr":0,"vp_xwoba":0.0,"h_streak":null,"hrr_streak":null,"book_hits_line":null},{"team":"COL","player":"McCarthy, Jake","proj_hits":1.234,"proj_tb":2.954,"proj_hr":0.183,"proj_bb":0.141,"l10_hit_pct":0.9,"vp_pa":5,"vp_h":1,"vp_hr":1,"vp_xwoba":0.54,"h_streak":null,"hrr_streak":null,"book_hits_line":null},{"team":"COL","player":"Moniak, Mickey","proj_hits":0.444,"proj_tb":0.907,"proj_hr":0.094,"proj_bb":0.067,"l10_hit_pct":0.2,"vp_pa":5,"vp_h":0,"vp_hr":0,"vp_xwoba":0.0,"h_streak":null,"hrr_streak":null,"book_hits_line":null},{"team":"COL","player":"Rumfield, TJ","proj_hits":1.171,"proj_tb":2.497,"proj_hr":0.22,"proj_bb":0.467,"l10_hit_pct":1.0,"vp_pa":3,"vp_h":1,"vp_hr":1,"vp_xwoba":0.667,"h_streak":null,"hrr_streak":null,"book_hits_line":null},{"team":"COL","player":"Tovar, Ezequiel","proj_hits":0.636,"proj_tb":1.275,"proj_hr":0.121,"proj_bb":0.131,"l10_hit_pct":0.4,"vp_pa":7,"vp_h":2,"vp_hr":1,"vp_xwoba":0.464,"h_streak":null,"hrr_streak":null,"book_hits_line":null},{"team":"MIA","player":"Caissie, Owen","proj_hits":0.973,"proj_tb":1.726,"proj_hr":0.183,"proj_bb":0.246,"l10_hit_pct":0.8,"vp_pa":null,"vp_h":null,"vp_hr":null,"vp_xwoba":null,"h_streak":null,"hrr_streak":null,"book_hits_line":null},{"team":"MIA","player":"Conine, Griffin","proj_hits":0.686,"proj_tb":1.421,"proj_hr":0.217,"proj_bb":0.356,"l10_hit_pct":0.5,"vp_pa":null,"vp_h":null,"vp_hr":null,"vp_xwoba":null,"h_streak":null,"hrr_streak":null,"book_hits_line":null},{"team":"MIA","player":"Edwards, Xavier","proj_hits":1.432,"proj_tb":1.878,"proj_hr":0.027,"proj_bb":0.353,"l10_hit_pct":0.9,"vp_pa":null,"vp_h":null,"vp_hr":null,"vp_xwoba":null,"h_streak":null,"hrr_streak":null,"book_hits_line":null},{"team":"MIA","player":"Lopez, Otto","proj_hits":1.408,"proj_tb":2.227,"proj_hr":0.14,"proj_bb":0.195,"l10_hit_pct":0.8,"vp_pa":3,"vp_h":1,"vp_hr":1,"vp_xwoba":0.667,"h_streak":null,"hrr_streak":null,"book_hits_line":null},{"team":"MIA","player":"Mack, Joe","proj_hits":0.928,"proj_tb":1.558,"proj_hr":0.193,"proj_bb":0.204,"l10_hit_pct":0.6,"vp_pa":null,"vp_h":null,"vp_hr":null,"vp_xwoba":null,"h_streak":null,"hrr_streak":null,"book_hits_line":null},{"team":"MIA","player":"Marsee, Jakob","proj_hits":0.762,"proj_tb":1.046,"proj_hr":0.019,"proj_bb":0.402,"l10_hit_pct":0.4,"vp_pa":3,"vp_h":0,"vp_hr":0,"vp_xwoba":0.0,"h_streak":null,"hrr_streak":null,"book_hits_line":null},{"team":"MIA","player":"Ruiz, Esteury","proj_hits":0.854,"proj_tb":1.532,"proj_hr":0.133,"proj_bb":0.107,"l10_hit_pct":0.4,"vp_pa":null,"vp_h":null,"vp_hr":null,"vp_xwoba":null,"h_streak":null,"hrr_streak":null,"book_hits_line":null},{"team":"MIA","player":"Sanoja, Javier","proj_hits":1.105,"proj_tb":1.612,"proj_hr":0.01,"proj_bb":0.046,"l10_hit_pct":0.5,"vp_pa":2,"vp_h":1,"vp_hr":0,"vp_xwoba":0.45,"h_streak":null,"hrr_streak":null,"book_hits_line":null},{"team":"MIA","player":"Stowers, Kyle","proj_hits":1.048,"proj_tb":1.923,"proj_hr":0.127,"proj_bb":0.462,"l10_hit_pct":0.7,"vp_pa":null,"vp_h":null,"vp_hr":null,"vp_xwoba":null,"h_streak":null,"hrr_streak":null,"book_hits_line":null}]},{"away_team":"TEX","home_team":"CLE","time":"6:40 PM ET","away_score":null,"home_score":null,"winner":"","lineup_status":"confirmed","batters":[{"team":"CLE","player":"Arias, Gabriel","proj_hits":0.734,"proj_tb":1.699,"proj_hr":0.153,"proj_bb":0.119,"l10_hit_pct":0.7,"vp_pa":null,"vp_h":null,"vp_hr":null,"vp_xwoba":null,"h_streak":null,"hrr_streak":null,"book_hits_line":null},{"team":"CLE","player":"Bailey, Patrick","proj_hits":0.485,"proj_tb":0.843,"proj_hr":0.015,"proj_bb":0.239,"l10_hit_pct":0.4,"vp_pa":2,"vp_h":0,"vp_hr":0,"vp_xwoba":0.0,"h_streak":null,"hrr_streak":null,"book_hits_line":null},{"team":"CLE","player":"Bazzana, Travis","proj_hits":0.784,"proj_tb":1.784,"proj_hr":0.172,"proj_bb":0.353,"l10_hit_pct":0.5,"vp_pa":3,"vp_h":0,"vp_hr":0,"vp_xwoba":0.233,"h_streak":null,"hrr_streak":null,"book_hits_line":null},{"team":"CLE","player":"Fry, David","proj_hits":0.289,"proj_tb":0.696,"proj_hr":0.09,"proj_bb":0.3,"l10_hit_pct":0.2,"vp_pa":null,"vp_h":null,"vp_hr":null,"vp_xwoba":null,"h_streak":null,"hrr_streak":null,"book_hits_line":null},{"team":"CLE","player":"Hedges, Austin","proj_hits":0.679,"proj_tb":1.238,"proj_hr":0.008,"proj_bb":0.077,"l10_hit_pct":0.7,"vp_pa":10,"vp_h":0,"vp_hr":0,"vp_xwoba":0.1,"h_streak":null,"hrr_streak":null,"book_hits_line":null},{"team":"CLE","player":"Hoskins, Rhys","proj_hits":0.496,"proj_tb":1.224,"proj_hr":0.108,"proj_bb":0.359,"l10_hit_pct":0.5,"vp_pa":29,"vp_h":5,"vp_hr":0,"vp_xwoba":0.3,"h_streak":null,"hrr_streak":null,"book_hits_line":null},{"team":"CLE","player":"Ingle, Cooper","proj_hits":0.283,"proj_tb":0.4,"proj_hr":0.0,"proj_bb":0.9,"l10_hit_pct":null,"vp_pa":null,"vp_h":null,"vp_hr":null,"vp_xwoba":null,"h_streak":null,"hrr_streak":null,"book_hits_line":null},{"team":"CLE","player":"Kwan, Steven","proj_hits":0.492,"proj_tb":0.869,"proj_hr":0.005,"proj_bb":0.292,"l10_hit_pct":0.6,"vp_pa":2,"vp_h":2,"vp_hr":0,"vp_xwoba":0.9,"h_streak":null,"hrr_streak":null,"book_hits_line":null},{"team":"CLE","player":"Manzardo, Kyle","proj_hits":0.585,"proj_tb":1.233,"proj_hr":0.105,"proj_bb":0.331,"l10_hit_pct":0.5,"vp_pa":3,"vp_h":0,"vp_hr":0,"vp_xwoba":0.0,"h_streak":null,"hrr_streak":null,"book_hits_line":null},{"team":"CLE","player":"Rocchio, Brayan","proj_hits":0.878,"proj_tb":1.675,"proj_hr":0.024,"proj_bb":0.174,"l10_hit_pct":0.8,"vp_pa":2,"vp_h":0,"vp_hr":0,"vp_xwoba":0.35,"h_streak":null,"hrr_streak":null,"book_hits_line":null},{"team":"CLE","player":"Schneemann, Daniel","proj_hits":0.419,"proj_tb":0.789,"proj_hr":0.035,"proj_bb":0.227,"l10_hit_pct":0.2,"vp_pa":3,"vp_h":0,"vp_hr":0,"vp_xwoba":0.0,"h_streak":null,"hrr_streak":null,"book_hits_line":null},{"team":"CLE","player":"Watson, Kahlil","proj_hits":0.825,"proj_tb":1.751,"proj_hr":0.117,"proj_bb":0.088,"l10_hit_pct":0.7,"vp_pa":null,"vp_h":null,"vp_hr":null,"vp_xwoba":null,"h_streak":null,"hrr_streak":null,"book_hits_line":null},{"team":"TEX","player":"Burger, Jake","proj_hits":0.997,"proj_tb":2.166,"proj_hr":0.249,"proj_bb":0.434,"l10_hit_pct":0.7,"vp_pa":5,"vp_h":2,"vp_hr":2,"vp_xwoba":0.783,"h_streak":null,"hrr_streak":null,"book_hits_line":null},{"team":"TEX","player":"Duran, Ezequiel","proj_hits":0.723,"proj_tb":1.379,"proj_hr":0.089,"proj_bb":0.155,"l10_hit_pct":0.5,"vp_pa":7,"vp_h":0,"vp_hr":0,"vp_xwoba":0.0,"h_streak":null,"hrr_streak":null,"book_hits_line":null},{"team":"TEX","player":"Foscue, Justin","proj_hits":0.855,"proj_tb":1.901,"proj_hr":0.183,"proj_bb":0.12,"l10_hit_pct":0.4,"vp_pa":null,"vp_h":null,"vp_hr":null,"vp_xwoba":null,"h_streak":null,"hrr_streak":null,"book_hits_line":null},{"team":"TEX","player":"Higashioka, Kyle","proj_hits":0.637,"proj_tb":1.217,"proj_hr":0.131,"proj_bb":0.445,"l10_hit_pct":0.4,"vp_pa":5,"vp_h":1,"vp_hr":0,"vp_xwoba":0.32,"h_streak":null,"hrr_streak":null,"book_hits_line":null},{"team":"TEX","player":"Jung, Josh","proj_hits":1.046,"proj_tb":1.887,"proj_hr":0.039,"proj_bb":0.334,"l10_hit_pct":0.6,"vp_pa":9,"vp_h":2,"vp_hr":0,"vp_xwoba":0.339,"h_streak":null,"hrr_streak":null,"book_hits_line":null},{"team":"TEX","player":"Lopez, Nicky","proj_hits":0.81,"proj_tb":1.11,"proj_hr":0.007,"proj_bb":0.108,"l10_hit_pct":0.9,"vp_pa":4,"vp_h":1,"vp_hr":0,"vp_xwoba":0.225,"h_streak":null,"hrr_streak":null,"book_hits_line":null},{"team":"TEX","player":"Nimmo, Brandon","proj_hits":1.11,"proj_tb":2.347,"proj_hr":0.129,"proj_bb":0.43,"l10_hit_pct":0.7,"vp_pa":6,"vp_h":0,"vp_hr":0,"vp_xwoba":0.117,"h_streak":null,"hrr_streak":null,"book_hits_line":null},{"team":"TEX","player":"Osuna, Alejandro","proj_hits":0.855,"proj_tb":1.235,"proj_hr":0.0,"proj_bb":0.215,"l10_hit_pct":0.7,"vp_pa":null,"vp_h":null,"vp_hr":null,"vp_xwoba":null,"h_streak":null,"hrr_streak":null,"book_hits_line":null},{"team":"TEX","player":"Pederson, Joc","proj_hits":0.799,"proj_tb":1.971,"proj_hr":0.317,"proj_bb":0.394,"l10_hit_pct":0.5,"vp_pa":3,"vp_h":0,"vp_hr":0,"vp_xwoba":0.0,"h_streak":null,"hrr_streak":null,"book_hits_line":null},{"team":"TEX","player":"Seager, Corey","proj_hits":0.747,"proj_tb":1.911,"proj_hr":0.319,"proj_bb":0.619,"l10_hit_pct":0.5,"vp_pa":15,"vp_h":4,"vp_hr":0,"vp_xwoba":0.31,"h_streak":null,"hrr_streak":null,"book_hits_line":null}]},{"away_team":"SD","home_team":"CHC","time":"8:05 PM ET","away_score":null,"home_score":null,"winner":"","lineup_status":"confirmed","batters":[{"team":"CHC","player":"Amaya, Miguel","proj_hits":0.637,"proj_tb":1.214,"proj_hr":0.031,"proj_bb":0.284,"l10_hit_pct":0.6,"vp_pa":null,"vp_h":null,"vp_hr":null,"vp_xwoba":null,"h_streak":null,"hrr_streak":null,"book_hits_line":null},{"team":"CHC","player":"Bregman, Alex","proj_hits":0.735,"proj_tb":1.149,"proj_hr":0.028,"proj_bb":0.632,"l10_hit_pct":0.5,"vp_pa":22,"vp_h":7,"vp_hr":2,"vp_xwoba":0.482,"h_streak":null,"hrr_streak":null,"book_hits_line":null},{"team":"CHC","player":"Busch, Michael","proj_hits":0.7,"proj_tb":1.358,"proj_hr":0.133,"proj_bb":0.715,"l10_hit_pct":0.5,"vp_pa":null,"vp_h":null,"vp_hr":null,"vp_xwoba":null,"h_streak":null,"hrr_streak":null,"book_hits_line":null},{"team":"CHC","player":"Conforto, Michael","proj_hits":0.513,"proj_tb":1.217,"proj_hr":0.129,"proj_bb":0.083,"l10_hit_pct":0.5,"vp_pa":null,"vp_h":null,"vp_hr":null,"vp_xwoba":null,"h_streak":null,"hrr_streak":null,"book_hits_line":null},{"team":"CHC","player":"Crow-Armstrong, Pete","proj_hits":1.014,"proj_tb":2.163,"proj_hr":0.226,"proj_bb":0.887,"l10_hit_pct":0.7,"vp_pa":null,"vp_h":null,"vp_hr":null,"vp_xwoba":null,"h_streak":null,"hrr_streak":null,"book_hits_line":null},{"team":"CHC","player":"Dean, Justin","proj_hits":0.39,"proj_tb":0.96,"proj_hr":0.0,"proj_bb":0.0,"l10_hit_pct":0.4,"vp_pa":null,"vp_h":null,"vp_hr":null,"vp_xwoba":null,"h_streak":null,"hrr_streak":null,"book_hits_line":null},{"team":"CHC","player":"Happ, Ian","proj_hits":0.877,"proj_tb":1.811,"proj_hr":0.154,"proj_bb":0.517,"l10_hit_pct":0.7,"vp_pa":null,"vp_h":null,"vp_hr":null,"vp_xwoba":null,"h_streak":null,"hrr_streak":null,"book_hits_line":null},{"team":"CHC","player":"Hoerner, Nico","proj_hits":1.069,"proj_tb":1.909,"proj_hr":0.017,"proj_bb":0.317,"l10_hit_pct":0.7,"vp_pa":null,"vp_h":null,"vp_hr":null,"vp_xwoba":null,"h_streak":null,"hrr_streak":null,"book_hits_line":null},{"team":"CHC","player":"Kelly, Carson","proj_hits":0.835,"proj_tb":1.614,"proj_hr":0.099,"proj_bb":0.512,"l10_hit_pct":0.5,"vp_pa":3,"vp_h":2,"vp_hr":0,"vp_xwoba":0.95,"h_streak":null,"hrr_streak":null,"book_hits_line":null},{"team":"CHC","player":"Suzuki, Seiya","proj_hits":1.11,"proj_tb":2.319,"proj_hr":0.223,"proj_bb":0.512,"l10_hit_pct":0.8,"vp_pa":null,"vp_h":null,"vp_hr":null,"vp_xwoba":null,"h_streak":null,"hrr_streak":null,"book_hits_line":null},{"team":"CHC","player":"Swanson, Dansby","proj_hits":0.71,"proj_tb":1.737,"proj_hr":0.195,"proj_bb":0.361,"l10_hit_pct":0.6,"vp_pa":null,"vp_h":null,"vp_hr":null,"vp_xwoba":null,"h_streak":null,"hrr_streak":null,"book_hits_line":null},{"team":"SD","player":"Andujar, Miguel","proj_hits":0.865,"proj_tb":1.287,"proj_hr":0.033,"proj_bb":0.153,"l10_hit_pct":0.3,"vp_pa":5,"vp_h":1,"vp_hr":0,"vp_xwoba":0.53,"h_streak":null,"hrr_streak":null,"book_hits_line":null},{"team":"SD","player":"Bogaerts, Xander","proj_hits":0.807,"proj_tb":1.341,"proj_hr":0.039,"proj_bb":0.648,"l10_hit_pct":0.5,"vp_pa":20,"vp_h":4,"vp_hr":1,"vp_xwoba":0.305,"h_streak":null,"hrr_streak":null,"book_hits_line":null},{"team":"SD","player":"Bowen, Jase","proj_hits":0.266,"proj_tb":0.389,"proj_hr":0.0,"proj_bb":0.161,"l10_hit_pct":0.2,"vp_pa":null,"vp_h":null,"vp_hr":null,"vp_xwoba":null,"h_streak":null,"hrr_streak":null,"book_hits_line":null},{"team":"SD","player":"Fermin, Freddy","proj_hits":0.538,"proj_tb":1.296,"proj_hr":0.222,"proj_bb":0.346,"l10_hit_pct":0.4,"vp_pa":9,"vp_h":2,"vp_hr":0,"vp_xwoba":0.239,"h_streak":null,"hrr_streak":null,"book_hits_line":null},{"team":"SD","player":"France, Ty","proj_hits":0.805,"proj_tb":1.885,"proj_hr":0.27,"proj_bb":0.166,"l10_hit_pct":0.6,"vp_pa":10,"vp_h":2,"vp_hr":0,"vp_xwoba":0.355,"h_streak":null,"hrr_streak":null,"book_hits_line":null},{"team":"SD","player":"Machado, Manny","proj_hits":0.89,"proj_tb":1.951,"proj_hr":0.224,"proj_bb":0.533,"l10_hit_pct":0.6,"vp_pa":17,"vp_h":8,"vp_hr":0,"vp_xwoba":0.506,"h_streak":null,"hrr_streak":null,"book_hits_line":null},{"team":"SD","player":"Merrill, Jackson","proj_hits":0.853,"proj_tb":1.529,"proj_hr":0.039,"proj_bb":0.173,"l10_hit_pct":0.6,"vp_pa":6,"vp_h":1,"vp_hr":0,"vp_xwoba":0.15,"h_streak":null,"hrr_streak":null,"book_hits_line":null},{"team":"SD","player":"Sheets, Gavin","proj_hits":0.913,"proj_tb":1.687,"proj_hr":0.201,"proj_bb":0.238,"l10_hit_pct":0.4,"vp_pa":null,"vp_h":null,"vp_hr":null,"vp_xwoba":null,"h_streak":null,"hrr_streak":null,"book_hits_line":null},{"team":"SD","player":"Song, Sung-Mun","proj_hits":0.682,"proj_tb":0.934,"proj_hr":0.0,"proj_bb":0.338,"l10_hit_pct":0.7,"vp_pa":null,"vp_h":null,"vp_hr":null,"vp_xwoba":null,"h_streak":null,"hrr_streak":null,"book_hits_line":null},{"team":"SD","player":"Tatis Jr., Fernando","proj_hits":1.101,"proj_tb":1.866,"proj_hr":0.093,"proj_bb":0.252,"l10_hit_pct":0.8,"vp_pa":9,"vp_h":2,"vp_hr":0,"vp_xwoba":0.3,"h_streak":null,"hrr_streak":null,"book_hits_line":null},{"team":"SD","player":"Taylor, Samad","proj_hits":1.251,"proj_tb":1.528,"proj_hr":0.019,"proj_bb":0.484,"l10_hit_pct":0.6,"vp_pa":2,"vp_h":1,"vp_hr":0,"vp_xwoba":0.45,"h_streak":null,"hrr_streak":null,"book_hits_line":null}]},{"away_team":"WSH","home_team":"BOS","time":"7:10 PM ET","away_score":null,"home_score":null,"winner":"","lineup_status":"confirmed","batters":[{"team":"BOS","player":"Abreu, Wilyer","proj_hits":0.935,"proj_tb":1.914,"proj_hr":0.17,"proj_bb":0.539,"l10_hit_pct":0.6,"vp_pa":null,"vp_h":null,"vp_hr":null,"vp_xwoba":null,"h_streak":null,"hrr_streak":null,"book_hits_line":null},{"team":"BOS","player":"Cheng, Tsung-Che","proj_hits":0.311,"proj_tb":0.514,"proj_hr":0.0,"proj_bb":0.133,"l10_hit_pct":0.286,"vp_pa":null,"vp_h":null,"vp_hr":null,"vp_xwoba":null,"h_streak":null,"hrr_streak":null,"book_hits_line":null},{"team":"BOS","player":"Contreras, Willson","proj_hits":1.22,"proj_tb":2.307,"proj_hr":0.271,"proj_bb":0.409,"l10_hit_pct":0.7,"vp_pa":null,"vp_h":null,"vp_hr":null,"vp_xwoba":null,"h_streak":null,"hrr_streak":null,"book_hits_line":null},{"team":"BOS","player":"Duran, Jarren","proj_hits":0.676,"proj_tb":0.921,"proj_hr":0.061,"proj_bb":0.138,"l10_hit_pct":0.4,"vp_pa":null,"vp_h":null,"vp_hr":null,"vp_xwoba":null,"h_streak":null,"hrr_streak":null,"book_hits_line":null},{"team":"BOS","player":"Durbin, Caleb","proj_hits":1.077,"proj_tb":1.985,"proj_hr":0.162,"proj_bb":0.245,"l10_hit_pct":0.9,"vp_pa":null,"vp_h":null,"vp_hr":null,"vp_xwoba":null,"h_streak":null,"hrr_streak":null,"book_hits_line":null},{"team":"BOS","player":"Eaton, Nate","proj_hits":0.593,"proj_tb":1.211,"proj_hr":0.109,"proj_bb":0.348,"l10_hit_pct":0.3,"vp_pa":null,"vp_h":null,"vp_hr":null,"vp_xwoba":null,"h_streak":null,"hrr_streak":null,"book_hits_line":null},{"team":"BOS","player":"Monasterio, Andruw","proj_hits":0.442,"proj_tb":0.831,"proj_hr":0.086,"proj_bb":0.119,"l10_hit_pct":0.3,"vp_pa":null,"vp_h":null,"vp_hr":null,"vp_xwoba":null,"h_streak":null,"hrr_streak":null,"book_hits_line":null},{"team":"BOS","player":"Rafaela, Ceddanne","proj_hits":1.189,"proj_tb":1.885,"proj_hr":0.035,"proj_bb":0.127,"l10_hit_pct":0.7,"vp_pa":null,"vp_h":null,"vp_hr":null,"vp_xwoba":null,"h_streak":null,"hrr_streak":null,"book_hits_line":null},{"team":"BOS","player":"Seigler, Anthony","proj_hits":1.212,"proj_tb":2.089,"proj_hr":0.11,"proj_bb":0.285,"l10_hit_pct":0.8,"vp_pa":null,"vp_h":null,"vp_hr":null,"vp_xwoba":null,"h_streak":null,"hrr_streak":null,"book_hits_line":null},{"team":"BOS","player":"Wong, Connor","proj_hits":0.768,"proj_tb":1.105,"proj_hr":0.076,"proj_bb":0.416,"l10_hit_pct":0.6,"vp_pa":null,"vp_h":null,"vp_hr":null,"vp_xwoba":null,"h_streak":null,"hrr_streak":null,"book_hits_line":null},{"team":"BOS","player":"Yoshida, Masataka","proj_hits":0.901,"proj_tb":1.5,"proj_hr":0.093,"proj_bb":0.21,"l10_hit_pct":0.7,"vp_pa":null,"vp_h":null,"vp_hr":null,"vp_xwoba":null,"h_streak":null,"hrr_streak":null,"book_hits_line":null},{"team":"WSH","player":"Abrams, CJ","proj_hits":0.722,"proj_tb":1.706,"proj_hr":0.321,"proj_bb":0.24,"l10_hit_pct":0.6,"vp_pa":null,"vp_h":null,"vp_hr":null,"vp_xwoba":null,"h_streak":null,"hrr_streak":null,"book_hits_line":null},{"team":"WSH","player":"Crews, Dylan","proj_hits":0.776,"proj_tb":1.357,"proj_hr":0.147,"proj_bb":0.156,"l10_hit_pct":0.7,"vp_pa":null,"vp_h":null,"vp_hr":null,"vp_xwoba":null,"h_streak":null,"hrr_streak":null,"book_hits_line":null},{"team":"WSH","player":"Lile, Daylen","proj_hits":0.681,"proj_tb":1.045,"proj_hr":0.037,"proj_bb":0.084,"l10_hit_pct":0.4,"vp_pa":null,"vp_h":null,"vp_hr":null,"vp_xwoba":null,"h_streak":null,"hrr_streak":null,"book_hits_line":null},{"team":"WSH","player":"Mead, Curtis","proj_hits":0.607,"proj_tb":1.352,"proj_hr":0.279,"proj_bb":0.113,"l10_hit_pct":0.7,"vp_pa":null,"vp_h":null,"vp_hr":null,"vp_xwoba":null,"h_streak":null,"hrr_streak":null,"book_hits_line":null},{"team":"WSH","player":"Millas, Drew","proj_hits":0.527,"proj_tb":0.765,"proj_hr":0.082,"proj_bb":0.198,"l10_hit_pct":0.6,"vp_pa":null,"vp_h":null,"vp_hr":null,"vp_xwoba":null,"h_streak":null,"hrr_streak":null,"book_hits_line":null},{"team":"WSH","player":"Ruiz, Keibert","proj_hits":0.658,"proj_tb":0.983,"proj_hr":0.043,"proj_bb":0.147,"l10_hit_pct":0.8,"vp_pa":null,"vp_h":null,"vp_hr":null,"vp_xwoba":null,"h_streak":null,"hrr_streak":null,"book_hits_line":null},{"team":"WSH","player":"Vivas, Jorbit","proj_hits":0.654,"proj_tb":1.022,"proj_hr":0.149,"proj_bb":0.242,"l10_hit_pct":0.6,"vp_pa":null,"vp_h":null,"vp_hr":null,"vp_xwoba":null,"h_streak":null,"hrr_streak":null,"book_hits_line":null},{"team":"WSH","player":"Wood, James","proj_hits":0.642,"proj_tb":1.342,"proj_hr":0.186,"proj_bb":0.555,"l10_hit_pct":0.5,"vp_pa":null,"vp_h":null,"vp_hr":null,"vp_xwoba":null,"h_streak":null,"hrr_streak":null,"book_hits_line":null},{"team":"WSH","player":"Young, Jacob","proj_hits":0.464,"proj_tb":0.749,"proj_hr":0.043,"proj_bb":0.048,"l10_hit_pct":0.4,"vp_pa":null,"vp_h":null,"vp_hr":null,"vp_xwoba":null,"h_streak":null,"hrr_streak":null,"book_hits_line":null}]},{"away_team":"CWS","home_team":"BAL","time":"6:35 PM ET","away_score":null,"home_score":null,"winner":"","lineup_status":"confirmed","batters":[{"team":"BAL","player":"Alexander, Blaze","proj_hits":1.064,"proj_tb":1.527,"proj_hr":0.081,"proj_bb":0.357,"l10_hit_pct":0.5,"vp_pa":2,"vp_h":1,"vp_hr":1,"vp_xwoba":1.0,"h_streak":null,"hrr_streak":null,"book_hits_line":null},{"team":"BAL","player":"Alonso, Pete","proj_hits":1.081,"proj_tb":2.19,"proj_hr":0.306,"proj_bb":0.744,"l10_hit_pct":0.6,"vp_pa":32,"vp_h":8,"vp_hr":0,"vp_xwoba":0.422,"h_streak":null,"hrr_streak":null,"book_hits_line":null},{"team":"BAL","player":"Basallo, Samuel","proj_hits":0.963,"proj_tb":1.771,"proj_hr":0.241,"proj_bb":0.258,"l10_hit_pct":0.5,"vp_pa":null,"vp_h":null,"vp_hr":null,"vp_xwoba":null,"h_streak":null,"hrr_streak":null,"book_hits_line":null},{"team":"BAL","player":"Cowser, Colton","proj_hits":0.815,"proj_tb":1.357,"proj_hr":0.136,"proj_bb":0.472,"l10_hit_pct":0.6,"vp_pa":6,"vp_h":0,"vp_hr":0,"vp_xwoba":0.117,"h_streak":null,"hrr_streak":null,"book_hits_line":null},{"team":"BAL","player":"Henderson, Gunnar","proj_hits":1.245,"proj_tb":2.217,"proj_hr":0.164,"proj_bb":0.448,"l10_hit_pct":0.6,"vp_pa":8,"vp_h":2,"vp_hr":1,"vp_xwoba":0.538,"h_streak":null,"hrr_streak":null,"book_hits_line":null},{"team":"BAL","player":"Holliday, Jackson","proj_hits":0.776,"proj_tb":1.526,"proj_hr":0.197,"proj_bb":0.355,"l10_hit_pct":0.6,"vp_pa":3,"vp_h":2,"vp_hr":0,"vp_xwoba":0.6,"h_streak":null,"hrr_streak":null,"book_hits_line":null},{"team":"BAL","player":"Mayo, Coby","proj_hits":0.702,"proj_tb":1.386,"proj_hr":0.144,"proj_bb":0.381,"l10_hit_pct":0.4,"vp_pa":3,"vp_h":1,"vp_hr":0,"vp_xwoba":0.3,"h_streak":null,"hrr_streak":null,"book_hits_line":null},{"team":"BAL","player":"O'Neill, Tyler","proj_hits":0.762,"proj_tb":1.227,"proj_hr":0.016,"proj_bb":0.419,"l10_hit_pct":0.6,"vp_pa":3,"vp_h":1,"vp_hr":0,"vp_xwoba":0.3,"h_streak":null,"hrr_streak":null,"book_hits_line":null},{"team":"BAL","player":"Taveras, Leody","proj_hits":0.946,"proj_tb":1.367,"proj_hr":0.01,"proj_bb":0.261,"l10_hit_pct":0.5,"vp_pa":2,"vp_h":1,"vp_hr":1,"vp_xwoba":1.0,"h_streak":null,"hrr_streak":null,"book_hits_line":null},{"team":"BAL","player":"Ward, Taylor","proj_hits":1.196,"proj_tb":1.592,"proj_hr":0.13,"proj_bb":0.509,"l10_hit_pct":0.6,"vp_pa":5,"vp_h":0,"vp_hr":0,"vp_xwoba":0.14,"h_streak":null,"hrr_streak":null,"book_hits_line":null},{"team":"CWS","player":"Benintendi, Andrew","proj_hits":0.697,"proj_tb":1.272,"proj_hr":0.147,"proj_bb":0.089,"l10_hit_pct":0.5,"vp_pa":null,"vp_h":null,"vp_hr":null,"vp_xwoba":null,"h_streak":null,"hrr_streak":null,"book_hits_line":null},{"team":"CWS","player":"Gonzalez, Jacob","proj_hits":0.695,"proj_tb":1.1,"proj_hr":0.091,"proj_bb":0.235,"l10_hit_pct":0.4,"vp_pa":null,"vp_h":null,"vp_hr":null,"vp_xwoba":null,"h_streak":null,"hrr_streak":null,"book_hits_line":null},{"team":"CWS","player":"Meidroth, Chase","proj_hits":1.03,"proj_tb":1.31,"proj_hr":0.027,"proj_bb":0.396,"l10_hit_pct":0.6,"vp_pa":null,"vp_h":null,"vp_hr":null,"vp_xwoba":null,"h_streak":null,"hrr_streak":null,"book_hits_line":null},{"team":"CWS","player":"Montgomery, Braden","proj_hits":0.866,"proj_tb":1.394,"proj_hr":0.083,"proj_bb":0.417,"l10_hit_pct":0.7,"vp_pa":null,"vp_h":null,"vp_hr":null,"vp_xwoba":null,"h_streak":null,"hrr_streak":null,"book_hits_line":null},{"team":"CWS","player":"Montgomery, Colson","proj_hits":0.701,"proj_tb":1.302,"proj_hr":0.09,"proj_bb":0.346,"l10_hit_pct":0.5,"vp_pa":null,"vp_h":null,"vp_hr":null,"vp_xwoba":null,"h_streak":null,"hrr_streak":null,"book_hits_line":null},{"team":"CWS","player":"Perez, Junior","proj_hits":0.5,"proj_tb":1.0,"proj_hr":0.167,"proj_bb":0.167,"l10_hit_pct":0.333,"vp_pa":null,"vp_h":null,"vp_hr":null,"vp_xwoba":null,"h_streak":null,"hrr_streak":null,"book_hits_line":null},{"team":"CWS","player":"Peters, Tristan","proj_hits":0.786,"proj_tb":1.244,"proj_hr":0.069,"proj_bb":0.209,"l10_hit_pct":0.5,"vp_pa":null,"vp_h":null,"vp_hr":null,"vp_xwoba":null,"h_streak":null,"hrr_streak":null,"book_hits_line":null},{"team":"CWS","player":"Teel, Kyle","proj_hits":0.893,"proj_tb":1.244,"proj_hr":0.107,"proj_bb":0.271,"l10_hit_pct":0.7,"vp_pa":null,"vp_h":null,"vp_hr":null,"vp_xwoba":null,"h_streak":null,"hrr_streak":null,"book_hits_line":null},{"team":"CWS","player":"Vargas, Miguel","proj_hits":0.999,"proj_tb":1.965,"proj_hr":0.25,"proj_bb":0.538,"l10_hit_pct":0.8,"vp_pa":null,"vp_h":null,"vp_hr":null,"vp_xwoba":null,"h_streak":null,"hrr_streak":null,"book_hits_line":null}]},{"away_team":"STL","home_team":"ATL","time":"7:15 PM ET","away_score":null,"home_score":null,"winner":"","lineup_status":"confirmed","batters":[{"team":"ATL","player":"Albies, Ozzie","proj_hits":1.01,"proj_tb":1.615,"proj_hr":0.177,"proj_bb":0.226,"l10_hit_pct":0.6,"vp_pa":5,"vp_h":0,"vp_hr":0,"vp_xwoba":0.14,"h_streak":null,"hrr_streak":null,"book_hits_line":null},{"team":"ATL","player":"Baldwin, Drake","proj_hits":0.518,"proj_tb":0.798,"proj_hr":0.093,"proj_bb":0.205,"l10_hit_pct":0.1,"vp_pa":2,"vp_h":2,"vp_hr":0,"vp_xwoba":0.9,"h_streak":null,"hrr_streak":null,"book_hits_line":null},{"team":"ATL","player":"Bart, Joey","proj_hits":0.914,"proj_tb":1.446,"proj_hr":0.142,"proj_bb":0.03,"l10_hit_pct":0.5,"vp_pa":6,"vp_h":1,"vp_hr":1,"vp_xwoba":0.333,"h_streak":null,"hrr_streak":null,"book_hits_line":null},{"team":"ATL","player":"Harris II, Michael","proj_hits":1.097,"proj_tb":1.675,"proj_hr":0.073,"proj_bb":0.166,"l10_hit_pct":0.7,"vp_pa":5,"vp_h":1,"vp_hr":0,"vp_xwoba":0.25,"h_streak":null,"hrr_streak":null,"book_hits_line":null},{"team":"ATL","player":"Kim, Ha-Seong","proj_hits":0.189,"proj_tb":0.176,"proj_hr":0.0,"proj_bb":0.355,"l10_hit_pct":0.1,"vp_pa":1,"vp_h":0,"vp_hr":0,"vp_xwoba":0.0,"h_streak":null,"hrr_streak":null,"book_hits_line":null},{"team":"ATL","player":"Mateo, Jorge","proj_hits":0.519,"proj_tb":0.689,"proj_hr":0.027,"proj_bb":0.045,"l10_hit_pct":0.2,"vp_pa":null,"vp_h":null,"vp_hr":null,"vp_xwoba":null,"h_streak":null,"hrr_streak":null,"book_hits_line":null},{"team":"ATL","player":"Olson, Matt","proj_hits":1.131,"proj_tb":1.667,"proj_hr":0.095,"proj_bb":0.32,"l10_hit_pct":0.6,"vp_pa":6,"vp_h":1,"vp_hr":0,"vp_xwoba":0.15,"h_streak":null,"hrr_streak":null,"book_hits_line":null},{"team":"ATL","player":"Riley, Austin","proj_hits":1.004,"proj_tb":1.204,"proj_hr":0.038,"proj_bb":0.289,"l10_hit_pct":0.5,"vp_pa":6,"vp_h":1,"vp_hr":0,"vp_xwoba":0.383,"h_streak":null,"hrr_streak":null,"book_hits_line":null},{"team":"ATL","player":"Smith, Dominic","proj_hits":0.921,"proj_tb":1.101,"proj_hr":0.037,"proj_bb":0.219,"l10_hit_pct":0.5,"vp_pa":null,"vp_h":null,"vp_hr":null,"vp_xwoba":null,"h_streak":null,"hrr_streak":null,"book_hits_line":null},{"team":"ATL","player":"Tellez, Rowdy","proj_hits":0.644,"proj_tb":1.455,"proj_hr":0.222,"proj_bb":0.048,"l10_hit_pct":0.4,"vp_pa":4,"vp_h":2,"vp_hr":1,"vp_xwoba":0.725,"h_streak":null,"hrr_streak":null,"book_hits_line":null},{"team":"ATL","player":"White, Eli","proj_hits":0.648,"proj_tb":1.066,"proj_hr":0.095,"proj_bb":0.109,"l10_hit_pct":0.5,"vp_pa":null,"vp_h":null,"vp_hr":null,"vp_xwoba":null,"h_streak":null,"hrr_streak":null,"book_hits_line":null},{"team":"ATL","player":"Yastrzemski, Mike","proj_hits":0.554,"proj_tb":0.914,"proj_hr":0.108,"proj_bb":0.277,"l10_hit_pct":0.3,"vp_pa":null,"vp_h":null,"vp_hr":null,"vp_xwoba":null,"h_streak":null,"hrr_streak":null,"book_hits_line":null},{"team":"STL","player":"Burleson, Alec","proj_hits":1.241,"proj_tb":1.813,"proj_hr":0.064,"proj_bb":0.401,"l10_hit_pct":0.6,"vp_pa":6,"vp_h":1,"vp_hr":0,"vp_xwoba":0.267,"h_streak":null,"hrr_streak":null,"book_hits_line":null},{"team":"STL","player":"Church, Nathan","proj_hits":0.954,"proj_tb":1.426,"proj_hr":0.034,"proj_bb":0.272,"l10_hit_pct":0.6,"vp_pa":null,"vp_h":null,"vp_hr":null,"vp_xwoba":null,"h_streak":null,"hrr_streak":null,"book_hits_line":null},{"team":"STL","player":"Crooks, Jimmy","proj_hits":0.481,"proj_tb":0.646,"proj_hr":0.022,"proj_bb":0.221,"l10_hit_pct":0.3,"vp_pa":null,"vp_h":null,"vp_hr":null,"vp_xwoba":null,"h_streak":null,"hrr_streak":null,"book_hits_line":null},{"team":"STL","player":"Jordan, Blaze","proj_hits":1.046,"proj_tb":1.467,"proj_hr":0.028,"proj_bb":0.171,"l10_hit_pct":0.5,"vp_pa":null,"vp_h":null,"vp_hr":null,"vp_xwoba":null,"h_streak":null,"hrr_streak":null,"book_hits_line":null},{"team":"STL","player":"Nootbaar, Lars","proj_hits":1.084,"proj_tb":1.856,"proj_hr":0.039,"proj_bb":0.582,"l10_hit_pct":0.8,"vp_pa":2,"vp_h":1,"vp_hr":0,"vp_xwoba":0.45,"h_streak":null,"hrr_streak":null,"book_hits_line":null},{"team":"STL","player":"Torres, Bryan","proj_hits":0.654,"proj_tb":1.422,"proj_hr":0.21,"proj_bb":0.314,"l10_hit_pct":0.4,"vp_pa":null,"vp_h":null,"vp_hr":null,"vp_xwoba":null,"h_streak":null,"hrr_streak":null,"book_hits_line":null},{"team":"STL","player":"Walker, Jordan","proj_hits":1.213,"proj_tb":1.579,"proj_hr":0.085,"proj_bb":0.325,"l10_hit_pct":0.6,"vp_pa":2,"vp_h":0,"vp_hr":0,"vp_xwoba":0.0,"h_streak":null,"hrr_streak":null,"book_hits_line":null},{"team":"STL","player":"Wetherholt, JJ","proj_hits":1.404,"proj_tb":2.226,"proj_hr":0.218,"proj_bb":0.313,"l10_hit_pct":0.6,"vp_pa":null,"vp_h":null,"vp_hr":null,"vp_xwoba":null,"h_streak":null,"hrr_streak":null,"book_hits_line":null},{"team":"STL","player":"Winn, Masyn","proj_hits":1.172,"proj_tb":1.628,"proj_hr":0.07,"proj_bb":0.269,"l10_hit_pct":0.9,"vp_pa":6,"vp_h":2,"vp_hr":0,"vp_xwoba":0.417,"h_streak":null,"hrr_streak":null,"book_hits_line":null}]},{"away_team":"LAD","home_team":"ATH","time":"9:40 PM ET","away_score":null,"home_score":null,"winner":"","lineup_status":"confirmed","batters":[{"team":"ATH","player":"Bolte, Henry","proj_hits":0.798,"proj_tb":1.13,"proj_hr":0.019,"proj_bb":0.44,"l10_hit_pct":0.7,"vp_pa":null,"vp_h":null,"vp_hr":null,"vp_xwoba":null,"h_streak":null,"hrr_streak":null,"book_hits_line":null},{"team":"ATH","player":"Heim, Jonah","proj_hits":0.536,"proj_tb":1.267,"proj_hr":0.229,"proj_bb":0.274,"l10_hit_pct":0.6,"vp_pa":null,"vp_h":null,"vp_hr":null,"vp_xwoba":null,"h_streak":null,"hrr_streak":null,"book_hits_line":null},{"team":"ATH","player":"Kurtz, Nick","proj_hits":0.722,"proj_tb":1.49,"proj_hr":0.179,"proj_bb":0.664,"l10_hit_pct":0.5,"vp_pa":1,"vp_h":0,"vp_hr":0,"vp_xwoba":0.0,"h_streak":null,"hrr_streak":null,"book_hits_line":null},{"team":"ATH","player":"Langeliers, Shea","proj_hits":0.764,"proj_tb":1.543,"proj_hr":0.187,"proj_bb":0.358,"l10_hit_pct":0.6,"vp_pa":1,"vp_h":1,"vp_hr":0,"vp_xwoba":0.9,"h_streak":null,"hrr_streak":null,"book_hits_line":null},{"team":"ATH","player":"Meneses, Joey","proj_hits":0.4,"proj_tb":0.465,"proj_hr":0.0,"proj_bb":0.271,"l10_hit_pct":0.4,"vp_pa":null,"vp_h":null,"vp_hr":null,"vp_xwoba":null,"h_streak":null,"hrr_streak":null,"book_hits_line":null},{"team":"ATH","player":"Thomas, Colby","proj_hits":0.325,"proj_tb":0.674,"proj_hr":0.115,"proj_bb":0.035,"l10_hit_pct":0.2,"vp_pa":null,"vp_h":null,"vp_hr":null,"vp_xwoba":null,"h_streak":null,"hrr_streak":null,"book_hits_line":null},{"team":"ATH","player":"Williams, Alika","proj_hits":0.829,"proj_tb":1.421,"proj_hr":0.019,"proj_bb":0.085,"l10_hit_pct":0.7,"vp_pa":null,"vp_h":null,"vp_hr":null,"vp_xwoba":null,"h_streak":null,"hrr_streak":null,"book_hits_line":null},{"team":"LAD","player":"Betts, Mookie","proj_hits":1.313,"proj_tb":2.75,"proj_hr":0.361,"proj_bb":0.283,"l10_hit_pct":0.9,"vp_pa":3,"vp_h":0,"vp_hr":0,"vp_xwoba":0.3,"h_streak":null,"hrr_streak":null,"book_hits_line":null},{"team":"LAD","player":"Call, Alex","proj_hits":0.708,"proj_tb":1.114,"proj_hr":0.076,"proj_bb":0.307,"l10_hit_pct":0.4,"vp_pa":null,"vp_h":null,"vp_hr":null,"vp_xwoba":null,"h_streak":null,"hrr_streak":null,"book_hits_line":null},{"team":"LAD","player":"Edman, Tommy","proj_hits":1.194,"proj_tb":1.945,"proj_hr":0.021,"proj_bb":0.39,"l10_hit_pct":0.6,"vp_pa":3,"vp_h":1,"vp_hr":0,"vp_xwoba":0.3,"h_streak":null,"hrr_streak":null,"book_hits_line":null},{"team":"LAD","player":"Freeland, Alex","proj_hits":0.774,"proj_tb":1.067,"proj_hr":0.019,"proj_bb":0.383,"l10_hit_pct":0.5,"vp_pa":null,"vp_h":null,"vp_hr":null,"vp_xwoba":null,"h_streak":null,"hrr_streak":null,"book_hits_line":null},{"team":"LAD","player":"Freeman, Freddie","proj_hits":1.374,"proj_tb":2.51,"proj_hr":0.153,"proj_bb":0.564,"l10_hit_pct":0.7,"vp_pa":5,"vp_h":1,"vp_hr":1,"vp_xwoba":0.54,"h_streak":null,"hrr_streak":null,"book_hits_line":null},{"team":"LAD","player":"Muncy, Max","proj_hits":0.861,"proj_tb":1.649,"proj_hr":0.168,"proj_bb":0.324,"l10_hit_pct":0.7,"vp_pa":null,"vp_h":null,"vp_hr":null,"vp_xwoba":null,"h_streak":null,"hrr_streak":null,"book_hits_line":null},{"team":"LAD","player":"Ohtani, Shohei","proj_hits":1.256,"proj_tb":2.565,"proj_hr":0.305,"proj_bb":0.518,"l10_hit_pct":0.8,"vp_pa":10,"vp_h":2,"vp_hr":0,"vp_xwoba":0.32,"h_streak":null,"hrr_streak":null,"book_hits_line":null},{"team":"LAD","player":"Pages, Andy","proj_hits":1.074,"proj_tb":2.053,"proj_hr":0.165,"proj_bb":0.462,"l10_hit_pct":0.6,"vp_pa":3,"vp_h":0,"vp_hr":0,"vp_xwoba":0.0,"h_streak":null,"hrr_streak":null,"book_hits_line":null},{"team":"LAD","player":"Robinson, Chuckie","proj_hits":0.288,"proj_tb":0.293,"proj_hr":0.0,"proj_bb":0.061,"l10_hit_pct":0.1,"vp_pa":null,"vp_h":null,"vp_hr":null,"vp_xwoba":null,"h_streak":null,"hrr_streak":null,"book_hits_line":null},{"team":"LAD","player":"Rojas, Miguel","proj_hits":0.616,"proj_tb":1.109,"proj_hr":0.079,"proj_bb":0.109,"l10_hit_pct":0.5,"vp_pa":3,"vp_h":0,"vp_hr":0,"vp_xwoba":0.0,"h_streak":null,"hrr_streak":null,"book_hits_line":null},{"team":"LAD","player":"Rushing, Dalton","proj_hits":0.721,"proj_tb":1.396,"proj_hr":0.164,"proj_bb":0.307,"l10_hit_pct":0.4,"vp_pa":null,"vp_h":null,"vp_hr":null,"vp_xwoba":null,"h_streak":null,"hrr_streak":null,"book_hits_line":null},{"team":"LAD","player":"Tucker, Kyle","proj_hits":1.195,"proj_tb":2.102,"proj_hr":0.201,"proj_bb":0.418,"l10_hit_pct":0.7,"vp_pa":2,"vp_h":0,"vp_hr":0,"vp_xwoba":0.0,"h_streak":null,"hrr_streak":null,"book_hits_line":null}]},{"away_team":"SF","home_team":"AZ","time":"9:40 PM ET","away_score":null,"home_score":null,"winner":"","lineup_status":"confirmed","batters":[{"team":"AZ","player":"Arenado, Nolan","proj_hits":1.107,"proj_tb":1.831,"proj_hr":0.135,"proj_bb":0.334,"l10_hit_pct":0.8,"vp_pa":6,"vp_h":2,"vp_hr":0,"vp_xwoba":0.358,"h_streak":null,"hrr_streak":null,"book_hits_line":null},{"team":"AZ","player":"Barrosa, Jorge","proj_hits":0.44,"proj_tb":0.932,"proj_hr":0.103,"proj_bb":0.148,"l10_hit_pct":0.3,"vp_pa":null,"vp_h":null,"vp_hr":null,"vp_xwoba":null,"h_streak":null,"hrr_streak":null,"book_hits_line":null},{"team":"AZ","player":"Carroll, Corbin","proj_hits":1.205,"proj_tb":2.222,"proj_hr":0.063,"proj_bb":0.484,"l10_hit_pct":0.6,"vp_pa":6,"vp_h":1,"vp_hr":0,"vp_xwoba":0.15,"h_streak":null,"hrr_streak":null,"book_hits_line":null},{"team":"AZ","player":"Gurriel Jr., Lourdes","proj_hits":1.015,"proj_tb":1.348,"proj_hr":0.01,"proj_bb":0.079,"l10_hit_pct":0.6,"vp_pa":3,"vp_h":1,"vp_hr":0,"vp_xwoba":0.533,"h_streak":null,"hrr_streak":null,"book_hits_line":null},{"team":"AZ","player":"Kepler, Max","proj_hits":0.594,"proj_tb":1.409,"proj_hr":0.176,"proj_bb":0.192,"l10_hit_pct":0.3,"vp_pa":4,"vp_h":2,"vp_hr":0,"vp_xwoba":0.45,"h_streak":null,"hrr_streak":null,"book_hits_line":null},{"team":"AZ","player":"Marte, Ketel","proj_hits":1.232,"proj_tb":2.461,"proj_hr":0.326,"proj_bb":0.394,"l10_hit_pct":0.8,"vp_pa":7,"vp_h":4,"vp_hr":0,"vp_xwoba":0.564,"h_streak":null,"hrr_streak":null,"book_hits_line":null},{"team":"AZ","player":"Moreno, Gabriel","proj_hits":1.104,"proj_tb":1.52,"proj_hr":0.041,"proj_bb":0.541,"l10_hit_pct":0.8,"vp_pa":4,"vp_h":2,"vp_hr":1,"vp_xwoba":0.813,"h_streak":null,"hrr_streak":null,"book_hits_line":null},{"team":"AZ","player":"Perdomo, Geraldo","proj_hits":1.13,"proj_tb":1.619,"proj_hr":0.075,"proj_bb":0.796,"l10_hit_pct":0.6,"vp_pa":8,"vp_h":3,"vp_hr":0,"vp_xwoba":0.513,"h_streak":null,"hrr_streak":null,"book_hits_line":null},{"team":"AZ","player":"Smith, Pavin","proj_hits":0.706,"proj_tb":1.151,"proj_hr":0.11,"proj_bb":0.261,"l10_hit_pct":0.4,"vp_pa":2,"vp_h":1,"vp_hr":0,"vp_xwoba":0.625,"h_streak":null,"hrr_streak":null,"book_hits_line":null},{"team":"SF","player":"Adames, Willy","proj_hits":1.145,"proj_tb":2.211,"proj_hr":0.249,"proj_bb":0.21,"l10_hit_pct":0.7,"vp_pa":10,"vp_h":3,"vp_hr":1,"vp_xwoba":0.625,"h_streak":null,"hrr_streak":null,"book_hits_line":null},{"team":"SF","player":"Arraez, Luis","proj_hits":1.507,"proj_tb":2.233,"proj_hr":0.079,"proj_bb":0.299,"l10_hit_pct":0.9,"vp_pa":22,"vp_h":10,"vp_hr":0,"vp_xwoba":0.473,"h_streak":null,"hrr_streak":null,"book_hits_line":null},{"team":"SF","player":"Bericoto, Victor","proj_hits":0.787,"proj_tb":1.744,"proj_hr":0.263,"proj_bb":0.076,"l10_hit_pct":0.6,"vp_pa":null,"vp_h":null,"vp_hr":null,"vp_xwoba":null,"h_streak":null,"hrr_streak":null,"book_hits_line":null},{"team":"SF","player":"Cavanaugh, Drew","proj_hits":0.767,"proj_tb":0.8,"proj_hr":0.0,"proj_bb":0.3,"l10_hit_pct":null,"vp_pa":null,"vp_h":null,"vp_hr":null,"vp_xwoba":null,"h_streak":null,"hrr_streak":null,"book_hits_line":null},{"team":"SF","player":"Chapman, Matt","proj_hits":0.756,"proj_tb":0.986,"proj_hr":0.033,"proj_bb":0.411,"l10_hit_pct":0.3,"vp_pa":8,"vp_h":0,"vp_hr":0,"vp_xwoba":0.0,"h_streak":null,"hrr_streak":null,"book_hits_line":null},{"team":"SF","player":"Cox, Jonah","proj_hits":0.708,"proj_tb":1.391,"proj_hr":0.121,"proj_bb":0.0,"l10_hit_pct":0.4,"vp_pa":null,"vp_h":null,"vp_hr":null,"vp_xwoba":null,"h_streak":null,"hrr_streak":null,"book_hits_line":null},{"team":"SF","player":"Devers, Rafael","proj_hits":0.972,"proj_tb":1.938,"proj_hr":0.253,"proj_bb":0.254,"l10_hit_pct":0.7,"vp_pa":6,"vp_h":0,"vp_hr":0,"vp_xwoba":0.117,"h_streak":null,"hrr_streak":null,"book_hits_line":null},{"team":"SF","player":"Eldridge, Bryce","proj_hits":0.984,"proj_tb":1.651,"proj_hr":0.127,"proj_bb":0.444,"l10_hit_pct":0.5,"vp_pa":3,"vp_h":0,"vp_hr":0,"vp_xwoba":0.0,"h_streak":null,"hrr_streak":null,"book_hits_line":null},{"team":"SF","player":"Gilbert, Drew","proj_hits":0.756,"proj_tb":1.02,"proj_hr":0.019,"proj_bb":0.293,"l10_hit_pct":0.4,"vp_pa":3,"vp_h":1,"vp_hr":0,"vp_xwoba":0.6,"h_streak":null,"hrr_streak":null,"book_hits_line":null},{"team":"SF","player":"Haase, Eric","proj_hits":0.313,"proj_tb":0.549,"proj_hr":0.068,"proj_bb":0.198,"l10_hit_pct":0.1,"vp_pa":null,"vp_h":null,"vp_hr":null,"vp_xwoba":null,"h_streak":null,"hrr_streak":null,"book_hits_line":null},{"team":"SF","player":"Schmitt, Casey","proj_hits":1.396,"proj_tb":2.423,"proj_hr":0.174,"proj_bb":0.027,"l10_hit_pct":0.7,"vp_pa":3,"vp_h":0,"vp_hr":0,"vp_xwoba":0.05,"h_streak":null,"hrr_streak":null,"book_hits_line":null}]}]}